Workbook

Sheet Kit_Solaire
A1: Ref LM | B1: Produit | C1: Prix de vente | D1: Quantiter | E1: Promo | F1: Remise peso | I1: Puissance théorique Totale | L1: Eco réaliser Total | N1: Eco moins Achat
A2: 85578551 | B2: Kit Solaire Master 370 Wcrete | C2: 579 | D2: 1 | E2: 360.48 | F2: -0.38 | I2: =(3*0.37)+3 -> 4.11 | J2: KWC | L2: =D10+D11+D12+D13+D14+D15+D16+D17 -> 2316.3827 | N2: =L2-L26 -> -3889.2673
A3: 85578552 | B3: Kit Solaire Exention 370 Wcrete | C3: 559 | D3: 2 | E3: =807.76/2 -> 403.88 | F3: -0.28
A4: 86147168 | B4: Prise Hombli Smart plug | C4: 29.9 | D4: 1 | E4: 25.41 | F4: -0.15 | G4: Date de mise en Service
C5: =C2+(C3*2)+C4 -> 1726.9 | D5: -0.31 | E5: =E2+(E3*2)+E4 -> 1193.65 | F5: =E5 -> 1193.65 | G5: 45054
B9: Amortisment | C9: eco theorique | D9: Eco réaliser anuelle | E9: Kwh Prod | F9: Reste a amortir | G9: Amorti Total en % | H9: Reste a amortir en % | I9: Kwh Injecter/Année | L9: Revente Facturé EDF | N9: Revente anuelle théorique | O9: KWH Facturé
B10: 2023 | C10: =SUM(Tableau3[Economi theorique]) -> 191.19217 | D10: =C10-(I10*J10) -> 180.70047 | E10: =Global!G15 -> 904.28 | F10: =L26-D10 -> 6024.9495 | G10: =D10/L26 -> 0.029118702 | H10: =F10/L26 -> 0.9708813 | I10: 50 | J10: =AVERAGE(Tableau3[Prix du KWH Sans abonement Prix Econmiser du KWH Solaire Produit]) -> 0.20983389 | K10: =I10*J10 -> 10.491695 | L10: 0 | N10: 0
B11: 2024 | C11: =SUM(Tableau37[Economi theorique]) -> 430.56206 | D11: =C11-(I11*J11) -> 304.41212 | E11: =Global!G31 -> 1709.17 | F11: =F10-D11 -> 5720.5374 | G11: =D11/L26+G10 -> 0.078172729 | H11: =F11/L26 -> 0.92182727 | I11: =556-I10 -> 506 | J11: =AVERAGE(Tableau37[Prix du KWH Sans abonement Prix Econmiser du KWH Solaire Produit]) -> 0.24930817 | K11: =I11*J11 -> 126.14993 | L11: 0 | N11: 0
B12: 2025 | C12: =SUM(Tableau378[Economi theorique]) -> 1358.947 | D12: =C12-(I12*J12)+L12 -> 968.18972 | E12: =Global!G47 -> 5120.12 | F12: =F11-D12 -> 4752.3477 | G12: =D12/L26+G11 -> 0.23419018 | H12: =F12/L26 -> 0.76580982 | I12: =3430-(I11+I10) -> 2874 | J12: =AVERAGE(Tableau378[Prix du KWH Sans abonement Prix Econmiser du KWH Solaire Produit]) -> 0.26538179 | K12: =(I12*J12)-L12 -> 390.75725 | L12: =1151.95-780 -> 371.95 | N12: =I12*F28 -> 366.7224 | O12: 2915
B13: 2026 | C13: =SUM(Tableau3789[Economi theorique]) -> 1238.1232 | D13: =C13-(I13*J13)+L13 -> 863.08042 | E13: =Global!G63 -> 4558.98 | F13: =F12-D13 -> 3889.2673 | G13: =D13/L26+G12 -> 0.37326996 | H13: =F13/L26 -> 0.62673004 | I13: =6038-I12-I11-I10 -> 2608 | J13: =AVERAGE(Tableau3789[Prix du KWH Sans abonement Prix Econmiser du KWH Solaire Produit]) -> 0.27468282 | K13: =(I13*J13)-L13 -> 375.0428 | L13: =O13*F28 -> 341.33 | O13: =I18-(448+O12) -> 2675
B14: 2027
B15: 2028
B16: 2029
B17: 2030
I18: =SUM(I10:I17) -> 6038 | L18: Facture TT EDF
I19: KWH TT Injecter | L19: =L12+L13+L14+L15+L16+L17 -> 713.28
A25: Facture | B25: Produit | C25: W/Unit | D25: KWC TT | E25: Prix ttc | F25: Prime | G25: TTC moins Prime | H25: Date mise en Service | L25: Investisment Totale
A26: 202406-296 | B26: Photovolataîque V4,02 mod Dualsun bifacial | C26: 500W | D26: 3 KWC | E26: =6320-528 -> 5792 | F26: =260*3 -> 780 | G26: =E26-F26 -> 5012 | H26: 45582 | L26: =G26+F5 -> 6205.65
F27: Revente KWH
F28: 0.1276

Sheet Global
A1: 2023 | B1: KWH Moyenne jour | C1: KWH Total | D1: Moyenne Jour € | E1: Total € | F1: Production Solaire /KWH Moyenne Jour | G1: Total Prod | H1: Prix du KWH Conso+Abo/KWH | I1: Economi theorique | J1: Reste a amortire | K1: Prix du KWH Sans abonement Prix Econmiser du KWH Solaire Produit
A2: Janvier | B2: =AVERAGE('2023'!$C$3:$C$33) -> 17.478387 | C2: =SUM('2023'!$C$3:$C$33) -> 541.83 | D2: =AVERAGE('2023'!$F$3:$F$33) -> 4.0558065 | E2: =SUM('2023'!$F$3:$F$33) -> 125.73 | F2: 0 | G2: =SUM('2023'!$G$3:$G$33) -> 0 | H2: =E2/C2 -> 0.23204695 | I2: =G2*K2 -> 0 | J2: =Kit_Solaire!F5-Global!I2 -> 1193.65
A3: Fevrier | B3: =AVERAGE('2023'!$C$34:$C$61) -> 15.966071 | C3: =SUM('2023'!$C$34:$C$61) -> 447.05 | D3: =AVERAGE('2023'!$F$34:$F$61) -> 3.8007143 | E3: =SUM('2023'!$F$34:$F$61) -> 106.42 | F3: 0 | G3: =SUM('2023'!$G$34:$G$61) -> 0 | H3: =E3/C3 -> 0.23804944 | I3: =G3*K3 -> 0 | J3: =J2-I3 -> 1193.65
A4: Mars | B4: =AVERAGE('2023'!$C$62:$C$92) -> 13.452581 | C4: =SUM('2023'!$C$62:$C$92) -> 417.03 | D4: =AVERAGE('2023'!$F$62:$F$92) -> 3.2296774 | E4: =SUM('2023'!$F$62:$F$92) -> 100.12 | F4: 0 | G4: =SUM('2023'!$G$62:$G$92) -> 0 | H4: =E4/C4 -> 0.24007865 | I4: =G4*K4 -> 0 | J4: =J3-I4 -> 1193.65
A5: Avril | B5: =AVERAGE('2023'!$C$93:$C$122) -> 13.560667 | C5: =SUM('2023'!$C$93:$C$122) -> 406.82 | D5: =AVERAGE('2023'!$F$93:$F$122) -> 3.208 | E5: =SUM('2023'!$F$93:$F$122) -> 96.24 | F5: 0 | G5: =SUM('2023'!$G$93:$G$122) -> 0 | H5: =E5/C5 -> 0.23656654 | I5: =G5*K5 -> 0 | J5: =J4-I5 -> 1193.65
A6: Mai | B6: =AVERAGE('2023'!$C$123:$C$153) -> 20.549677 | C6: =SUM('2023'!$C$123:$C$153) -> 637.04 | D6: =AVERAGE('2023'!$F$123:$F$153) -> 4.5612903 | E6: =SUM('2023'!$F$123:$F$153) -> 141.4 | F6: =AVERAGE('2023'!$G$123:$G$153) -> 4.4166667 | G6: =SUM('2023'!$G$123:$G$153) -> 106 | H6: =E6/C6 -> 0.22196408 | I6: =G6*K6 -> 21.4649 | J6: =J5-I6 -> 1172.1851 | K6: =SUM('2023'!$D$123:$D$153)/C6 -> 0.20249906
A7: Juin | B7: =AVERAGE('2023'!$C$154:$C$183) -> 10.078333 | C7: =SUM('2023'!$C$154:$C$183) -> 302.35 | D7: =AVERAGE('2023'!$F$154:$F$183) -> 2.5786667 | E7: =SUM('2023'!$F$154:$F$183) -> 77.36 | F7: =AVERAGE('2023'!$G$154:$G$183) -> 5.399 | G7: =SUM('2023'!$G$154:$G$183) -> 161.97 | H7: =E7/C7 -> 0.25586241 | I7: =G7*K7 -> 35.013591 | J7: =J6-I7 -> 1137.1715 | K7: =SUM('2023'!$D$154:$D$183)/C7 -> 0.21617331
A8: Juillet | B8: =AVERAGE('2023'!$C$184:$C$214) -> 11.411935 | C8: =SUM('2023'!$C$184:$C$214) -> 353.77 | D8: =AVERAGE('2023'!$F$184:$F$214) -> 2.8445161 | E8: =SUM('2023'!$F$184:$F$214) -> 88.18 | F8: =AVERAGE('2023'!$G$184:$G$214) -> 5.8035484 | G8: =SUM('2023'!$G$184:$G$214) -> 179.91 | H8: =E8/C8 -> 0.24925799 | I8: =G8*K8 -> 38.537976 | J8: =J7-I8 -> 1098.6335 | K8: =SUM('2023'!$D$184:$D$214)/C8 -> 0.21420697
A9: Août | B9: =AVERAGE('2023'!$C$215:$C$245) -> 12.496774 | C9: =SUM('2023'!$C$215:$C$245) -> 387.4 | D9: =AVERAGE('2023'!$F$215:$F$245) -> 3.0496774 | E9: =SUM('2023'!$F$215:$F$245) -> 94.54 | F9: =AVERAGE('2023'!$G$215:$G$245) -> 5.1006452 | G9: =SUM('2023'!$G$215:$G$245) -> 158.12 | H9: =E9/C9 -> 0.24403717 | I9: =G9*K9 -> 33.526011 | J9: =J8-I9 -> 1065.1075 | K9: =SUM('2023'!$D$215:$D$245)/C9 -> 0.21202891
A10: Septembre | B10: =AVERAGE('2023'!$C$246:$C$275) -> 11.298333 | C10: =SUM('2023'!$C$246:$C$275) -> 338.95 | D10: =AVERAGE('2023'!$F$246:$F$275) -> 2.8016667 | E10: =SUM('2023'!$F$246:$F$275) -> 84.05 | F10: =AVERAGE('2023'!$G$246:$G$275) -> 4.5493333 | G10: =SUM('2023'!$G$246:$G$275) -> 136.48 | H10: =E10/C10 -> 0.24797168 | I10: =G10*K10 -> 29.011311 | J10: =J9-I10 -> 1036.0962 | K10: =SUM('2023'!$D$246:$D$275)/C10 -> 0.21256823
A11: Octobre | B11: =AVERAGE('2023'!$C$276:$C$306) -> 10.137742 | C11: =SUM('2023'!$C$276:$C$306) -> 314.27 | D11: =AVERAGE('2023'!$F$276:$F$306) -> 2.5283871 | E11: =SUM('2023'!$F$276:$F$306) -> 78.38 | F11: =AVERAGE('2023'!$G$276:$G$306) -> 2.8816129 | G11: =SUM('2023'!$G$276:$G$306) -> 89.33 | H11: =E11/C11 -> 0.24940338 | I11: =G11*K11 -> 18.754553 | J11: =J10-I11 -> 1017.3417 | K11: =SUM('2023'!$D$276:$D$306)/C11 -> 0.20994686
A12: Novembre | B12: =AVERAGE('2023'!$C$307:$C$336) -> 12.218333 | C12: =SUM('2023'!$C$307:$C$336) -> 366.55 | D12: =AVERAGE('2023'!$F$307:$F$336) -> 2.895 | E12: =SUM('2023'!$F$307:$F$336) -> 86.85 | F12: =AVERAGE('2023'!$G$307:$G$336) -> 1.4156667 | G12: =SUM('2023'!$G$307:$G$336) -> 42.47 | H12: =E12/C12 -> 0.23693903 | I12: =G12*K12 -> 8.6724308 | J12: =J11-I12 -> 1008.6692 | K12: =SUM('2023'!$D$307:$D$336)/C12 -> 0.20420134
A13: Décembre | B13: =AVERAGE('2023'!$C$337:$C$367) -> 14.319677 | C13: =SUM('2023'!$C$337:$C$367) -> 443.91 | D13: =AVERAGE('2023'!$F$337:$F$367) -> 3.3648387 | E13: =SUM('2023'!$F$337:$F$367) -> 104.31 | F13: =AVERAGE('2023'!$G$337:$G$367) -> 0.96774194 | G13: =SUM('2023'!$G$337:$G$367) -> 30 | H13: =E13/C13 -> 0.23498006 | I13: =G13*K13 -> 6.2113942 | J13: =J12-I13 -> 1002.4578 | K13: =SUM('2023'!$D$337:$D$367)/C13 -> 0.20704647
B14: KWH J | C14: KWH Tt | D14: Moy / Mois | E14: Total | G14: Total | M14: Solaire utiliser | N14: eco
B15: =C15/365 -> 13.58074 | C15: =C2+C3+C4+C5+C6+C7+C8+C9+C10+C11+C12+C13 -> 4956.97 | D15: =E15/12 -> 98.631667 | E15: =E2+E3+E4+E5+E6+E7+E8+E9+E10+E11+E12+E13 -> 1183.58 | G15: =SUM(G6:G13) -> 904.28 | M15: =G15-Global!I10 -> 875.26869 | N15: =M15*Kit_Solaire!J10 -> 183.66104
A17: 2024 | B17: KWH Moyenne jour | C17: KWH Total | D17: Moyenne Jour € | E17: Total € | F17: Production Solaire /KWH Moyenne Jour | G17: Total Prod | H17: Prix du KWH Conso+Abo/KWH | I17: Economi theorique | J17: Reste a amortire | K17: Prix du KWH Sans abonement Prix Econmiser du KWH Solaire Produit
A18: Janvier | B18: =AVERAGE('2024'!$C$3:$C$33) -> 14.15129 | C18: =SUM('2024'!$C$3:$C$33) -> 438.69 | D18: =AVERAGE('2024'!$F$3:$F$33) -> 3.3216129 | E18: =SUM('2024'!$F$3:$F$33) -> 102.97 | F18: =AVERAGE('2024'!$G$3:$G$33) -> 1.2541935 | G18: =SUM('2024'!$G$3:$G$33) -> 38.88 | H18: =E18/C18 -> 0.23472156 | I18: =G18*K18 -> 8.0269931 | J18: =J13-Tableau37[[#This Row],[Economi theorique]] -> 994.43084 | K18: =SUM('2024'!$D$3:$D$33)/C18 -> 0.20645558
A19: Fevrier | B19: =AVERAGE('2024'!$C$34:$C$62) -> 13.664138 | C19: =SUM('2024'!$C$34:$C$62) -> 396.26 | D19: =AVERAGE('2024'!$F$34:$F$62) -> 3.8468966 | E19: =SUM('2024'!$F$34:$F$62) -> 111.56 | F19: =AVERAGE('2024'!$G$34:$G$62) -> 1.8148276 | G19: =SUM('2024'!$G$34:$G$62) -> 52.63 | H19: =E19/C19 -> 0.28153233 | I19: =G19*K19 -> 13.276371 | J19: =J18-Tableau37[[#This Row],[Economi theorique]] -> 981.15447 | K19: =SUM('2024'!$D$34:$D$62)/C19 -> 0.25225862
A20: Mars | B20: =AVERAGE('2024'!$C$63:$C$93) -> 11.438387 | C20: =SUM('2024'!$C$63:$C$93) -> 354.59 | D20: =AVERAGE('2024'!$F$63:$F$93) -> 3.173871 | E20: =SUM('2024'!$F$63:$F$93) -> 98.39 | F20: =AVERAGE('2024'!$G$63:$G$93) -> 3.5819355 | G20: =SUM('2024'!$G$63:$G$93) -> 111.04 | H20: =E20/C20 -> 0.27747539 | I20: =G20*K20 -> 25.863091 | J20: =J19-Tableau37[[#This Row],[Economi theorique]] -> 955.29138 | K20: =SUM('2024'!$D$63:$D$92)/C20 -> 0.23291689
A21: Avril | B21: =AVERAGE('2024'!$C$94:$C$123) -> 9.565 | C21: =SUM('2024'!$C$94:$C$123) -> 286.95 | D21: =AVERAGE('2024'!$F$94:$F$123) -> 2.7993333 | E21: =SUM('2024'!$F$94:$F$123) -> 83.98 | F21: =AVERAGE('2024'!$G$94:$G$123) -> 4.5416667 | G21: =SUM('2024'!$G$94:$G$123) -> 136.25 | H21: =E21/C21 -> 0.29266423 | I21: =G21*K21 -> 34.177644 | J21: =J20-Tableau37[[#This Row],[Economi theorique]] -> 921.11373 | K21: =SUM('2024'!$D$94:$D$123)/C21 -> 0.25084509
A22: Mai | B22: =AVERAGE('2024'!$C$124:$C$154) -> 8.386129 | C22: =SUM('2024'!$C$124:$C$154) -> 259.97 | D22: =AVERAGE('2024'!$F$124:$F$154) -> 2.5732258 | E22: =SUM('2024'!$F$124:$F$154) -> 79.77 | F22: =AVERAGE('2024'!$G$124:$G$154) -> 4.636129 | G22: =SUM('2024'!$G$124:$G$154) -> 143.72 | H22: =E22/C22 -> 0.3068431 | I22: =G22*K22 -> 37.244361 | J22: =J21-Tableau37[[#This Row],[Economi theorique]] -> 883.86937 | K22: =SUM('2024'!$D$124:$D$154)/C22 -> 0.25914529
A23: Juin | B23: =AVERAGE('2024'!$C$155:$C$184) -> 9.5536667 | C23: =SUM('2024'!$C$155:$C$184) -> 286.61 | D23: =AVERAGE('2024'!$F$155:$F$184) -> 2.9186667 | E23: =SUM('2024'!$F$155:$F$184) -> 87.56 | F23: =AVERAGE('2024'!$G$155:$G$184) -> 5.1673333 | G23: =SUM('2024'!$G$155:$G$184) -> 155.02 | H23: =E23/C23 -> 0.30550225 | I23: =G23*K23 -> 40.868467 | J23: =J22-Tableau37[[#This Row],[Economi theorique]] -> 843.00091 | K23: =SUM('2024'!$D$155:$D$184)/C23 -> 0.26363351
A24: Juillet | B24: =AVERAGE('2024'!$C$185:$C$215) -> 10.115806 | C24: =SUM('2024'!$C$185:$C$215) -> 313.59 | D24: =AVERAGE('2024'!$F$185:$F$215) -> 3.0651613 | E24: =SUM('2024'!$F$185:$F$215) -> 95.02 | F24: =AVERAGE('2024'!$G$185:$G$215) -> 5.7870968 | G24: =SUM('2024'!$G$185:$G$215) -> 179.4 | H24: =E24/C24 -> 0.30300711 | I24: =G24*K24 -> 45.852578 | J24: =J23-Tableau37[[#This Row],[Economi theorique]] -> 797.14833 | K24: =SUM('2024'!$D$185:$D$214)/C24 -> 0.25558851
A25: Août | B25: =AVERAGE('2024'!$C$216:$C$246) -> 10.943871 | C25: =SUM('2024'!$C$216:$C$246) -> 339.26 | D25: =AVERAGE('2024'!$F$216:$F$246) -> 3.2916129 | E25: =SUM('2024'!$F$216:$F$246) -> 102.04 | F25: =AVERAGE('2024'!$G$216:$G$246) -> 5.4703226 | G25: =SUM('2024'!$G$216:$G$246) -> 169.58 | H25: =E25/C25 -> 0.30077227 | I25: =G25*K25 -> 44.806789 | J25: =J24-Tableau37[[#This Row],[Economi theorique]] -> 752.34154 | K25: =SUM('2024'!$D$216:$D$246)/C25 -> 0.26422213
A26: Septembre | B26: =AVERAGE('2024'!$C$247:$C$276) -> 9.8856667 | C26: =SUM('2024'!$C$247:$C$276) -> 296.57 | D26: =AVERAGE('2024'!$F$247:$F$276) -> 3.001 | E26: =SUM('2024'!$F$247:$F$276) -> 90.03 | F26: =AVERAGE('2024'!$G$247:$G$276) -> 3.5243333 | G26: =SUM('2024'!$G$247:$G$276) -> 105.73 | H26: =E26/C26 -> 0.30357083 | I26: =G26*K26 -> 27.81843 | J26: =J25-Tableau37[[#This Row],[Economi theorique]] -> 724.52311 | K26: =SUM('2024'!$D$247:$D$276)/C26 -> 0.2631082
A27: Octobre | B27: =AVERAGE('2024'!$C$277:$C$307) -> 8.3187097 | C27: =SUM('2024'!$C$277:$C$307) -> 257.88 | D27: =AVERAGE('2024'!$F$277:$F$307) -> 2.4467742 | E27: =SUM('2024'!$F$277:$F$307) -> 75.85 | F27: =AVERAGE('2024'!$G$277:$G$307) -> 6.2090323 | G27: =SUM('2024'!$G$277:$G$307) -> 192.48 | H27: =E27/C27 -> 0.29412905 | I27: =G27*K27 -> 47.358678 | J27: =J26-Tableau37[[#This Row],[Economi theorique]]+Kit_Solaire!G26 -> 5689.1644 | K27: =SUM('2024'!$D$277:$D$307)/C27 -> 0.24604467
A28: Novembre | B28: =AVERAGE('2024'!$C$308:$C$337) -> 8.664 | C28: =SUM('2024'!$C$308:$C$337) -> 259.92 | D28: =AVERAGE('2024'!$F$308:$F$337) -> 2.5293333 | E28: =SUM('2024'!$F$308:$F$337) -> 75.88 | F28: =AVERAGE('2024'!$G$308:$G$337) -> 8.7926667 | G28: =SUM('2024'!$G$308:$G$337) -> 263.78 | H28: =E28/C28 -> 0.29193598 | I28: =G28*K28 -> 64.828664 | J28: =J27-Tableau37[[#This Row],[Economi theorique]]+Kit_Solaire!G28 -> 5624.3358 | K28: =SUM('2024'!$D$308:$D$337)/C28 -> 0.24576793
A29: Décembre | B29: =AVERAGE('2024'!$C$338:$C$368) -> 13.239677 | C29: =SUM('2024'!$C$338:$C$368) -> 410.43 | D29: =AVERAGE('2024'!$F$338:$F$368) -> 3.7325806 | E29: =SUM('2024'!$F$338:$F$368) -> 115.71 | F29: =AVERAGE('2024'!$G$338:$G$368) -> 5.1825806 | G29: =SUM('2024'!$G$338:$G$368) -> 160.66 | H29: =E29/C29 -> 0.28192384 | I29: =G29*K29 -> 40.439989 | J29: =J28-Tableau37[[#This Row],[Economi theorique]]+Kit_Solaire!G29 -> 5583.8958 | K29: =SUM('2024'!$D$338:$D$368)/C29 -> 0.25171162
B30: KWH J | C30: KWH Tt | D30: Moy/Mois | E30: Total | G30: Total | M30: Solaire utiliser | N30: eco
B31: =C31/366 -> 10.657705 | C31: =C18+C19+C20+C21+C22+C23+C24+C25+C26+C27+C28+C29 -> 3900.72 | D31: =E31/12 -> 93.23 | E31: =SUM(Tableau37[Total €]) -> 1118.76 | G31: =SUM(Tableau37[Total Prod]) -> 1709.17 | M31: =G31-Kit_Solaire!I11 -> 1203.17 | N31: =M31*Kit_Solaire!J11 -> 299.96011
A33: 2025 | B33: KWH Moyenne jour | C33: KWH Total | D33: Moyenne Jour € | E33: Total € | F33: Production Solaire /KWH Moyenne Jour | G33: Total Prod | H33: Prix du KWH Conso+Abo/KWH | I33: Economi theorique | J33: Reste a amortire | K33: Prix du KWH Sans abonement Prix Econmiser du KWH Solaire Produit
A34: Janvier | B34: =AVERAGE('2025'!$C$2:$C$32) -> 13.050323 | C34: =SUM('2025'!C2:C32) -> 404.56 | D34: =AVERAGE('2025'!$F$2:$F$32) -> 3.6867742 | E34: =SUM('2025'!F2:F32) -> 114.29 | F34: =AVERAGE('2025'!$I$2:$I$32) -> 6.3606452 | G34: =SUM('2025'!I2:I32) -> 197.18 | H34: =E34/C34 -> 0.28250445 | I34: =G34*K34 -> 49.056177 | J34: =Kit_Solaire!L26-(Kit_Solaire!D10+Kit_Solaire!D11)-Tableau378[[#This Row],[Economi theorique]] -> 5671.4812 | K34: =SUM('2025'!$D$2:$D$32)/C34 -> 0.24878881
A35: Fevrier | B35: =AVERAGE('2025'!$C$33:$C$60) -> 9.6325 | C35: =SUM('2025'!C33:C60) -> 269.71 | D35: =AVERAGE('2025'!$F$33:$F$60) -> 2.8228571 | E35: =SUM('2025'!F33:F60) -> 79.04 | F35: =AVERAGE('2025'!$I$33:$I$60) -> 10.989643 | G35: =SUM('2025'!I33:I60) -> 307.71 | H35: =E35/C35 -> 0.2930555 | I35: =G35*K35 -> 76.120319 | J35: =J34-I35 -> 5595.3609 | K35: =SUM('2025'!$D$33:$D$60)/C35 -> 0.24737681
A36: Mars | B36: =AVERAGE('2025'!$C$61:$C$91) -> 8.0583871 | C36: =SUM('2025'!C61:C91) -> 249.81 | D36: =AVERAGE('2025'!$F$61:$F$91) -> 2.33 | E36: =SUM('2025'!F61:F91) -> 72.23 | F36: =AVERAGE('2025'!$I$61:$I$91) -> 13.615806 | G36: =SUM('2025'!I61:I91) -> 422.09 | H36: =E36/C36 -> 0.28913975 | I36: =G36*K36 -> 98.99625 | J36: =J35-I36 -> 5496.3647 | K36: =SUM('2025'!$D$61:$D$91)/C36 -> 0.23453825
A37: Avril | B37: =AVERAGE('2025'!$C$92:$C$121) -> 5.138 | C37: =SUM('2025'!C92:C121) -> 154.14 | D37: =AVERAGE('2025'!$F$92:$F$121) -> 1.8066667 | E37: =SUM('2025'!F92:F121) -> 54.2 | F37: =AVERAGE('2025'!$I$92:$I$121) -> 17.836667 | G37: =SUM('2025'!I92:I121) -> 535.1 | H37: =E37/C37 -> 0.35162839 | I37: =G37*K37 -> 142.3323 | J37: =J36-I37 -> 5354.0324 | K37: =SUM('2025'!$D$92:$D$121)/C37 -> 0.26599196
A38: Mai | B38: =AVERAGE('2025'!$C$122:$C$152) -> 5.0219355 | C38: =SUM('2025'!C122:C152) -> 155.68 | D38: =AVERAGE('2025'!$F$122:$F$152) -> 1.7867742 | E38: =SUM('2025'!F122:F152) -> 55.39 | F38: =AVERAGE('2025'!$I$122:$I$152) -> 19.824516 | G38: =SUM('2025'!I122:I152) -> 614.56 | H38: =E38/C38 -> 0.35579394 | I38: =G38*K38 -> 164.81166 | J38: =J37-I38 -> 5189.2207 | K38: =SUM('2025'!$D$122:$D$152)/C38 -> 0.26817831
A39: Juin | B39: =AVERAGE('2025'!$C$153:$C$182) -> 5.592 | C39: =SUM('2025'!C153:C182) -> 167.76 | D39: =AVERAGE('2025'!$F$153:$F$182) -> 1.9153333 | E39: =SUM('2025'!F153:F182) -> 57.46 | F39: =AVERAGE('2025'!$I$153:$I$182) -> 21.814667 | G39: =SUM('2025'!I153:I182) -> 654.44 | H39: =E39/C39 -> 0.34251311 | I39: =G39*K39 -> 172.66043 | J39: =J38-I39 -> 5016.5603 | K39: =SUM('2025'!$D$153:$D$182)/C39 -> 0.26382928
A40: Juillet | B40: =AVERAGE('2025'!$C$183:$C$213) -> 4.2358065 | C40: =SUM('2025'!C183:C213) -> 131.31 | D40: =AVERAGE('2025'!$F$183:$F$213) -> 1.5529032 | E40: =SUM('2025'!F183:F213) -> 48.14 | F40: =AVERAGE('2025'!$I$183:$I$213) -> 20.122258 | G40: =SUM('2025'!I183:I213) -> 623.79 | H40: =E40/C40 -> 0.36661336 | I40: =G40*K40 -> 163.89273 | J40: =J39-I40 -> 4852.6675 | K40: =SUM('2025'!$D$183:$D$213)/C40 -> 0.26273703
A41: Août | B41: =AVERAGE('2025'!$C$214:$C$244) -> 7.9406452 | C41: =SUM('2025'!C214:C244) -> 246.16 | D41: =AVERAGE('2025'!$F$214:$F$244) -> 2.6358065 | E41: =SUM('2025'!F214:F244) -> 81.71 | F41: =AVERAGE('2025'!$I$214:$I$244) -> 18.965161 | G41: =SUM('2025'!I214:I244) -> 587.92 | H41: =E41/C41 -> 0.33193858 | I41: =G41*K41 -> 162.57603 | J41: =J40-I41 -> 4690.0915 | K41: =SUM('2025'!$D$214:$D$244)/C41 -> 0.27652746
A42: Septembre | B42: =AVERAGE('2025'!$C$245:$C$274) -> 5.0663333 | C42: =SUM('2025'!C245:C274) -> 151.99 | D42: =AVERAGE('2025'!$F$245:$F$274) -> 1.8816667 | E42: =SUM('2025'!F245:F274) -> 56.45 | F42: =AVERAGE('2025'!$I$245:$I$274) -> 14.692 | G42: =SUM('2025'!I245:I274) -> 440.76 | H42: =E42/C42 -> 0.37140601 | I42: =G42*K42 -> 125.42187 | J42: =J41-I42 -> 4564.6696 | K42: =SUM('2025'!$D$245:$D$274)/C42 -> 0.28455819
A43: Octobre | B43: =AVERAGE('2025'!$C$275:$C$305) -> 6.6393548 | C43: =SUM('2025'!C275:C305) -> 205.82 | D43: =AVERAGE('2025'!$F$275:$F$305) -> 2.2603226 | E43: =SUM('2025'!F275:F305) -> 70.07 | F43: =AVERAGE('2025'!$I$275:$I$305) -> 12.001935 | G43: =SUM('2025'!I275:I305) -> 372.06 | H43: =E43/C43 -> 0.34044311 | I43: =G43*K43 -> 102.00829 | J43: =J42-I43 -> 4462.6613 | K43: =SUM('2025'!$D$275:$D$305)/C43 -> 0.27417161
A44: Novembre | B44: =AVERAGE('2025'!$C$306:$C$335) -> 10.751667 | C44: =SUM('2025'!C306:C335) -> 322.55 | D44: =AVERAGE('2025'!$F$306:$F$335) -> 3.348 | E44: =SUM('2025'!F306:F335) -> 100.44 | F44: =AVERAGE('2025'!$I$306:$I$335) -> 7.2676667 | G44: =SUM('2025'!I306:I335) -> 218.03 | H44: =E44/C44 -> 0.31139358 | I44: =G44*K44 -> 58.970508 | J44: =J43-I44 -> 4403.6908 | K44: =SUM('2025'!$D$306:$D$335)/C44 -> 0.27046969
A45: Décembre | B45: =AVERAGE('2025'!$C$336:$C$366) -> 11.630968 | C45: =SUM('2025'!C336:C366) -> 360.56 | D45: =AVERAGE('2025'!$F$336:$F$366) -> 3.7829032 | E45: =SUM('2025'!F336:F366) -> 117.27 | F45: =AVERAGE('2025'!$I$336:$I$366) -> 4.7251613 | G45: =SUM('2025'!I336:I366) -> 146.48 | H45: =E45/C45 -> 0.32524406 | I45: =G45*K45 -> 42.100406 | J45: =J44-I45 -> 4361.5904 | K45: =SUM('2025'!$D$336:$D$366)/C45 -> 0.28741402
B46: KWH J | C46: KWH Tt | D46: Moy/Mois | E46: Total | G46: Total | M46: Solaire utiliser | N46: eco
B47: =C47/365 -> 7.7261644 | C47: =SUM(Tableau378[KWH Total]) -> 2820.05 | D47: =E47/12 -> 75.5575 | E47: =SUM(Tableau378[Total €]) -> 906.69 | G47: =SUM(Tableau378[Total Prod]) -> 5120.12 | M47: =Global!G47-Kit_Solaire!I12 -> 2246.12 | N47: =M47*Kit_Solaire!J12 -> 596.07934
A49: 2026 | B49: KWH Moyenne jour | C49: KWH Total | D49: Moyenne Jour € | E49: Total € | F49: Production Solaire /KWH Moyenne Jour | G49: Total Prod | H49: Prix du KWH Conso+Abo/KWH | I49: Economi theorique | J49: Reste a amortire | K49: Prix du KWH Sans abonement Prix Econmiser du KWH Solaire Produit
A50: Janvier | B50: =AVERAGE('2026'!C2:C32) -> 11.240323 | C50: =SUM('2026'!C2:C32) -> 348.45 | D50: =AVERAGE('2026'!F2:F32) -> 3.6922581 | E50: =SUM('2026'!F2:F32) -> 114.46 | F50: =AVERAGE('2026'!I2:I32) -> 5.1041935 | G50: =SUM('2026'!I2:I32) -> 158.23 | H50: =E50/C50 -> 0.32848328 | I50: =G50*K50 -> 45.782031 | J50: =J44-Tableau3789[[#This Row],[Economi theorique]] -> 4357.9088 | K50: =SUM('2026'!D2:D32)/Tableau3789[[#This Row],[KWH Total]] -> 0.2893385
A51: Fevrier | B51: =AVERAGE('2026'!C33:C60) -> 9.2607143 | C51: =SUM('2026'!C33:C60) -> 259.3 | D51: =AVERAGE('2026'!F33:F60) -> 3.0975 | E51: =SUM('2026'!F33:F60) -> 86.73 | F51: =AVERAGE('2026'!I33:I60) -> 8.9503571 | G51: =SUM('2026'!I33:I60) -> 250.61 | H51: =E51/C51 -> 0.33447744 | I51: =G51*K51 -> 71.916275 | J51: =J50-Tableau3789[[#This Row],[Economi theorique]] -> 4285.9925 | K51: =SUM('2026'!D33:D60)/Tableau3789[[#This Row],[KWH Total]] -> 0.28696491
A52: Mars | B52: =AVERAGE('2026'!C61:C91) -> 7.8287097 | C52: =SUM('2026'!C61:C91) -> 242.69 | D52: =AVERAGE('2026'!F61:F91) -> 2.6058065 | E52: =SUM('2026'!F61:F91) -> 80.78 | F52: =AVERAGE('2026'!I61:I91) -> 14.680645 | G52: =SUM('2026'!I61:I91) -> 455.1 | H52: =E52/C52 -> 0.33285261 | I52: =G52*K52 -> 125.90306 | J52: =J51-Tableau3789[[#This Row],[Economi theorique]] -> 4160.0895 | K52: =SUM('2026'!D61:D91)/Tableau3789[[#This Row],[KWH Total]] -> 0.27664922
A53: Avril | B53: =AVERAGE('2026'!C92:C121) -> 5.4793333 | C53: =SUM('2026'!C92:C121) -> 164.38 | D53: =AVERAGE('2026'!F92:F121) -> 2.0013333 | E53: =SUM('2026'!F92:F121) -> 60.04 | F53: =AVERAGE('2026'!I92:I121) -> 19.368333 | G53: =SUM('2026'!I92:I121) -> 581.05 | H53: =E53/C53 -> 0.36525125 | I53: =G53*K53 -> 165.56991 | J53: =J52-Tableau3789[[#This Row],[Economi theorique]] -> 3994.5196 | K53: =SUM('2026'!D92:D121)/Tableau3789[[#This Row],[KWH Total]] -> 0.28494951
A54: Mai | B54: =AVERAGE('2026'!C122:C152) -> 4.7780645 | C54: =SUM('2026'!C122:C152) -> 148.12 | D54: =AVERAGE('2026'!F122:F152) -> 1.7612903 | E54: =SUM('2026'!F122:F152) -> 54.6 | F54: =AVERAGE('2026'!I122:I152) -> 20.050645 | G54: =SUM('2026'!I122:I152) -> 621.57 | H54: =E54/C54 -> 0.36862004 | I54: =G54*K54 -> 171.88433 | J54: =J53-Tableau3789[[#This Row],[Economi theorique]] -> 3822.6352 | K54: =SUM('2026'!D122:D152)/Tableau3789[[#This Row],[KWH Total]] -> 0.27653254
A55: Juin | B55: =AVERAGE('2026'!C153:C182) -> 6.5373333 | C55: =SUM('2026'!C153:C182) -> 196.12 | D55: =AVERAGE('2026'!F153:F182) -> 2.2073333 | E55: =SUM('2026'!F153:F182) -> 66.22 | F55: =AVERAGE('2026'!I153:I182) -> 22.495333 | G55: =SUM('2026'!I153:I182) -> 674.86 | H55: =E55/C55 -> 0.33765042 | I55: =G55*K55 -> 182.44482 | J55: =J54-Tableau3789[[#This Row],[Economi theorique]] -> 3640.1904 | K55: =SUM('2026'!D153:D182)/Tableau3789[[#This Row],[KWH Total]] -> 0.27034469
A56: Juillet | B56: =AVERAGE('2026'!C183:C213) -> 5.4035484 | C56: =SUM('2026'!C183:C213) -> 167.51 | D56: =AVERAGE('2026'!F183:F213) -> 1.7890323 | E56: =SUM('2026'!F183:F213) -> 55.46 | F56: =AVERAGE('2026'!I183:I213) -> 21.73871 | G56: =SUM('2026'!I183:I213) -> 673.9 | H56: =E56/C56 -> 0.33108471 | I56: =G56*K56 -> 168.24368 | J56: =J55-Tableau3789[[#This Row],[Economi theorique]] -> 3471.9467 | K56: =SUM('2026'!D183:D213)/Tableau3789[[#This Row],[KWH Total]] -> 0.24965674
A57: Août | B57: =AVERAGE('2026'!C214:C244) -> 7.5619355 | C57: =SUM('2026'!C214:C244) -> 234.42 | D57: =AVERAGE('2026'!F214:F244) -> 2.4006452 | E57: =SUM('2026'!F214:F244) -> 74.42 | F57: =AVERAGE('2026'!I214:I244) -> 20.297419 | G57: =SUM('2026'!I214:I244) -> 629.22 | H57: =E57/C57 -> 0.31746438 | I57: =G57*K57 -> 163.14304 | J57: =J56-Tableau3789[[#This Row],[Economi theorique]] -> 3308.8037 | K57: =SUM('2026'!D214:D244)/Tableau3789[[#This Row],[KWH Total]] -> 0.25927822
A58: Septembre | B58: =AVERAGE('2026'!C245:C274) -> 4.8734615 | C58: =SUM('2026'!C245:C274) -> 126.71 | D58: =AVERAGE('2026'!F245:F274) -> 1.7969231 | E58: =SUM('2026'!F245:F274) -> 46.72 | F58: =AVERAGE('2026'!I245:I274) -> 19.786154 | G58: =SUM('2026'!I245:I274) -> 514.44 | H58: =E58/C58 -> 0.36871597 | I58: =G58*K58 -> 143.23608 | J58: =J57-Tableau3789[[#This Row],[Economi theorique]] -> 3165.5676 | K58: =SUM('2026'!D245:D274)/Tableau3789[[#This Row],[KWH Total]] -> 0.27843106
A59: Octobre
A60: Novembre
A61: Décembre
B62: KWH J | C62: KWH Tt | D62: Moy/Mois | E62: Total | G62: Total | M62: Solaire utiliser | N62: eco
C63: =SUM(Tableau3789[KWH Total]) -> 1887.7 | E63: =SUM(Tableau3789[Total €]) -> 639.43 | G63: =SUM(Tableau3789[Total Prod]) -> 4558.98 | M63: =Global!G63-Kit_Solaire!I28 -> 4558.98 | N63: =M63*Kit_Solaire!J13 -> 1252.2735

Sheet 2026
A1: Jour | B1: Date | C1: KWH | D1: Conso € | E1: Abonnement € | F1: Total €/J | G1: Prod Solaire /KWH Cab | H1: Prod Solaire /KWH Maison | I1: Prod Solaire Total
A2: Jeudi | B2: 46023 | C2: 10.2 | D2: =Tableau9[[#This Row],[Total €/J]]-Tableau9[[#This Row],[Abonnement €]] -> 2.76 | E2: 0.44 | F2: 3.2 | G2: 1.63 | H2: 6.73 | I2: =Tableau9[[#This Row],[Prod Solaire /KWH Maison]]+Tableau9[[#This Row],[Prod Solaire /KWH Cab]] -> 8.36
A3: Vendredi | B3: 46024 | C3: 9.66 | D3: =Tableau9[[#This Row],[Total €/J]]-Tableau9[[#This Row],[Abonnement €]] -> 2.72 | E3: 0.44 | F3: 3.16 | G3: 1.2 | H3: 6.33 | I3: =Tableau9[[#This Row],[Prod Solaire /KWH Maison]]+Tableau9[[#This Row],[Prod Solaire /KWH Cab]] -> 7.53
A4: Samedi | B4: 46025 | C4: 12.64 | D4: =Tableau9[[#This Row],[Total €/J]]-Tableau9[[#This Row],[Abonnement €]] -> 3.66 | E4: 0.44 | F4: 4.1 | G4: 0.86 | H4: 3.76 | I4: =Tableau9[[#This Row],[Prod Solaire /KWH Maison]]+Tableau9[[#This Row],[Prod Solaire /KWH Cab]] -> 4.62
A5: Dimanche | B5: 46026 | C5: 11.84 | D5: =Tableau9[[#This Row],[Total €/J]]-Tableau9[[#This Row],[Abonnement €]] -> 3.52 | E5: 0.44 | F5: 3.96 | G5: 1.35 | H5: 6.47 | I5: =Tableau9[[#This Row],[Prod Solaire /KWH Maison]]+Tableau9[[#This Row],[Prod Solaire /KWH Cab]] -> 7.82
A6: Lundi | B6: 46027 | C6: 11.75 | D6: =Tableau9[[#This Row],[Total €/J]]-Tableau9[[#This Row],[Abonnement €]] -> 3.43 | E6: 0.44 | F6: 3.87 | G6: 0.41 | H6: 1.09 | I6: =Tableau9[[#This Row],[Prod Solaire /KWH Maison]]+Tableau9[[#This Row],[Prod Solaire /KWH Cab]] -> 1.5
A7: Mardi | B7: 46028 | C7: 11.37 | D7: =Tableau9[[#This Row],[Total €/J]]-Tableau9[[#This Row],[Abonnement €]] -> 3.24 | E7: 0.44 | F7: 3.68 | G7: 1.29 | H7: 4.79 | I7: =Tableau9[[#This Row],[Prod Solaire /KWH Maison]]+Tableau9[[#This Row],[Prod Solaire /KWH Cab]] -> 6.08
A8: Mercredi | B8: 46029 | C8: 10.4 | D8: =Tableau9[[#This Row],[Total €/J]]-Tableau9[[#This Row],[Abonnement €]] -> 2.86 | E8: 0.44 | F8: 3.3 | G8: 0.86 | H8: 3.33 | I8: =Tableau9[[#This Row],[Prod Solaire /KWH Maison]]+Tableau9[[#This Row],[Prod Solaire /KWH Cab]] -> 4.19
A9: Jeudi | B9: 46030 | C9: 17.43 | D9: =Tableau9[[#This Row],[Total €/J]]-Tableau9[[#This Row],[Abonnement €]] -> 4.93 | E9: 0.44 | F9: 5.37 | G9: 0.49 | H9: 1.29 | I9: =Tableau9[[#This Row],[Prod Solaire /KWH Maison]]+Tableau9[[#This Row],[Prod Solaire /KWH Cab]] -> 1.78
A10: Vendredi | B10: 46031 | C10: 13.97 | D10: =Tableau9[[#This Row],[Total €/J]]-Tableau9[[#This Row],[Abonnement €]] -> 4.05 | E10: 0.44 | F10: 4.49 | G10: 0.44 | H10: 1.17 | I10: =Tableau9[[#This Row],[Prod Solaire /KWH Maison]]+Tableau9[[#This Row],[Prod Solaire /KWH Cab]] -> 1.61
A11: Samedi | B11: 46032 | C11: 18.04 | D11: =Tableau9[[#This Row],[Total €/J]]-Tableau9[[#This Row],[Abonnement €]] -> 5.37 | E11: 0.44 | F11: 5.81 | G11: 1.02 | H11: 3.27 | I11: =Tableau9[[#This Row],[Prod Solaire /KWH Maison]]+Tableau9[[#This Row],[Prod Solaire /KWH Cab]] -> 4.29
A12: Dimanche | B12: 46033 | C12: 7.91 | D12: =Tableau9[[#This Row],[Total €/J]]-Tableau9[[#This Row],[Abonnement €]] -> 2.31 | E12: 0.44 | F12: 2.75 | G12: 1.61 | H12: 6.47 | I12: =Tableau9[[#This Row],[Prod Solaire /KWH Maison]]+Tableau9[[#This Row],[Prod Solaire /KWH Cab]] -> 8.08
A13: Lundi | B13: 46034 | C13: 15.53 | D13: =Tableau9[[#This Row],[Total €/J]]-Tableau9[[#This Row],[Abonnement €]] -> 4.53 | E13: 0.44 | F13: 4.97 | G13: 1.2 | H13: 3.54 | I13: =Tableau9[[#This Row],[Prod Solaire /KWH Maison]]+Tableau9[[#This Row],[Prod Solaire /KWH Cab]] -> 4.74
... A270: Samedi | B270: 46291 | C270: 3.52 | D270: =Tableau9[[#This Row],[Total €/J]]-Tableau9[[#This Row],[Abonnement €]] -> 0.94 | E270: 0.44 | F270: 1.38 | G270: 4.63 | H270: 13 | I270: =Tableau9[[#This Row],[Prod Solaire /KWH Maison]]+Tableau9[[#This Row],[Prod Solaire /KWH Cab]] -> 17.63
A271: Dimanche | B271: 46292
A272: Lundi | B272: 46293
A273: Mardi | B273: 46294
A274: Mercredi | B274: 46295
A275: Jeudi | B275: 46296
A276: Vendredi | B276: 46297
A277: Samedi | B277: 46298
A278: Dimanche | B278: 46299
A279: Lundi | B279: 46300
A280: Mardi | B280: 46301
A281: Mercredi | B281: 46302
A282: Jeudi | B282: 46303
... A366: Jeudi | B366: 46387

Sheet 2025
A1: Jour | B1: Date | C1: KWH | D1: Conso € | E1: Abonnement € | F1: Total €/J | G1: Prod Solaire /KWH Cab | H1: Prod Solaire /KWH Maison | I1: Prod Solaire Total
A2: Mercredi | B2: 45658 | C2: 11.94 | D2: =Tableau5[[#This Row],[Total €/J]]-Tableau5[[#This Row],[Abonnement €]] -> 2.93 | E2: 0.44 | F2: 3.37 | G2: 1.53 | H2: 8.04 | I2: =Tableau5[[#This Row],[Prod Solaire /KWH Maison]]+Tableau5[[#This Row],[Prod Solaire /KWH Cab]] -> 9.57
A3: Jeudi | B3: 45659 | C3: 19.77 | D3: =Tableau5[[#This Row],[Total €/J]]-Tableau5[[#This Row],[Abonnement €]] -> 5.11 | E3: 0.44 | F3: 5.55 | G3: 0.98 | H3: 3.28 | I3: =Tableau5[[#This Row],[Prod Solaire /KWH Maison]]+Tableau5[[#This Row],[Prod Solaire /KWH Cab]] -> 4.26
A4: Vendredi | B4: 45660 | C4: 13.3 | D4: =Tableau5[[#This Row],[Total €/J]]-Tableau5[[#This Row],[Abonnement €]] -> 3.33 | E4: 0.44 | F4: 3.77 | G4: 0.67 | H4: 1.81 | I4: =Tableau5[[#This Row],[Prod Solaire /KWH Maison]]+Tableau5[[#This Row],[Prod Solaire /KWH Cab]] -> 2.48
A5: Samedi | B5: 45661 | C5: 9.84 | D5: =Tableau5[[#This Row],[Total €/J]]-Tableau5[[#This Row],[Abonnement €]] -> 2.45 | E5: 0.44 | F5: 2.89 | G5: 0.3 | H5: 0.79 | I5: =Tableau5[[#This Row],[Prod Solaire /KWH Maison]]+Tableau5[[#This Row],[Prod Solaire /KWH Cab]] -> 1.09
A6: Dimanche | B6: 45662 | C6: 12.71 | D6: =Tableau5[[#This Row],[Total €/J]]-Tableau5[[#This Row],[Abonnement €]] -> 3.13 | E6: 0.44 | F6: 3.57 | G6: 1.05 | H6: 3.25 | I6: =Tableau5[[#This Row],[Prod Solaire /KWH Maison]]+Tableau5[[#This Row],[Prod Solaire /KWH Cab]] -> 4.3
A7: Lundi | B7: 45663 | C7: 10.68 | D7: =Tableau5[[#This Row],[Total €/J]]-Tableau5[[#This Row],[Abonnement €]] -> 2.62 | E7: 0.44 | F7: 3.06 | G7: 0.62 | H7: 2.48 | I7: =Tableau5[[#This Row],[Prod Solaire /KWH Maison]]+Tableau5[[#This Row],[Prod Solaire /KWH Cab]] -> 3.1
A8: Mardi | B8: 45664 | C8: 11.16 | D8: =Tableau5[[#This Row],[Total €/J]]-Tableau5[[#This Row],[Abonnement €]] -> 2.7 | E8: 0.44 | F8: 3.14 | G8: 1.5 | H8: 4.9 | I8: =Tableau5[[#This Row],[Prod Solaire /KWH Maison]]+Tableau5[[#This Row],[Prod Solaire /KWH Cab]] -> 6.4
A9: Mercredi | B9: 45665 | C9: 15.87 | D9: =Tableau5[[#This Row],[Total €/J]]-Tableau5[[#This Row],[Abonnement €]] -> 4.2 | E9: 0.44 | F9: 4.64 | G9: 1.26 | H9: 5.31 | I9: =Tableau5[[#This Row],[Prod Solaire /KWH Maison]]+Tableau5[[#This Row],[Prod Solaire /KWH Cab]] -> 6.57
A10: Jeudi | B10: 45666 | C10: 10.62 | D10: =Tableau5[[#This Row],[Total €/J]]-Tableau5[[#This Row],[Abonnement €]] -> 2.65 | E10: 0.44 | F10: 3.09 | G10: 0.88 | H10: 2.46 | I10: =Tableau5[[#This Row],[Prod Solaire /KWH Maison]]+Tableau5[[#This Row],[Prod Solaire /KWH Cab]] -> 3.34
A11: Vendredi | B11: 45667 | C11: 11.95 | D11: =Tableau5[[#This Row],[Total €/J]]-Tableau5[[#This Row],[Abonnement €]] -> 3.03 | E11: 0.44 | F11: 3.47 | G11: 0.66 | H11: 1.75 | I11: =Tableau5[[#This Row],[Prod Solaire /KWH Maison]]+Tableau5[[#This Row],[Prod Solaire /KWH Cab]] -> 2.41
A12: Samedi | B12: 45668 | C12: 19.19 | D12: =Tableau5[[#This Row],[Total €/J]]-Tableau5[[#This Row],[Abonnement €]] -> 4.95 | E12: 0.44 | F12: 5.39 | G12: 0.66 | H12: 2 | I12: =Tableau5[[#This Row],[Prod Solaire /KWH Maison]]+Tableau5[[#This Row],[Prod Solaire /KWH Cab]] -> 2.66
A13: Dimanche | B13: 45669 | C13: 11.12 | D13: =Tableau5[[#This Row],[Total €/J]]-Tableau5[[#This Row],[Abonnement €]] -> 2.74 | E13: 0.44 | F13: 3.18 | G13: 1.85 | H13: 9.5 | I13: =Tableau5[[#This Row],[Prod Solaire /KWH Maison]]+Tableau5[[#This Row],[Prod Solaire /KWH Cab]] -> 11.35
... A98: Lundi | B98: 45754 | C98: 7.66 | D98: =Tableau5[[#This Row],[Total €/J]]-Tableau5[[#This Row],[Abonnement €]] -> 2 | E98: 0.44 | F98: 2.44 | G98: 3.89 | H98: 8.23 | I98: =Tableau5[[#This Row],[Prod Solaire /KWH Maison]]+Tableau5[[#This Row],[Prod Solaire /KWH Cab]] -> 12.12
A99: Mardi | B99: 45755 | C99: 6.8 | D99: =Tableau5[[#This Row],[Total €/J]]-Tableau5[[#This Row],[Abonnement €]] -> 1.65 | E99: 0.44 | F99: 2.09 | G99: 6.09 | H99: 18.6 | I99: =Tableau5[[#This Row],[Prod Solaire /KWH Maison]]+Tableau5[[#This Row],[Prod Solaire /KWH Cab]] -> 24.69 | J99: 4 h en journée
A100: Mercredi | B100: 45756 | C100: 5.33 | D100: =Tableau5[[#This Row],[Total €/J]]-Tableau5[[#This Row],[Abonnement €]] -> 1.25 | E100: 0.44 | F100: 1.69 | G100: 5.38 | H100: 16.2 | I100: =Tableau5[[#This Row],[Prod Solaire /KWH Maison]]+Tableau5[[#This Row],[Prod Solaire /KWH Cab]] -> 21.58
A101: Jeudi | B101: 45757 | C101: 5.27 | D101: =Tableau5[[#This Row],[Total €/J]]-Tableau5[[#This Row],[Abonnement €]] -> 1.31 | E101: 0.44 | F101: 1.75 | G101: 5.78 | H101: 17.7 | I101: =Tableau5[[#This Row],[Prod Solaire /KWH Maison]]+Tableau5[[#This Row],[Prod Solaire /KWH Cab]] -> 23.48
A102: Vendredi | B102: 45758 | C102: 3.96 | D102: =Tableau5[[#This Row],[Total €/J]]-Tableau5[[#This Row],[Abonnement €]] -> 1.02 | E102: 0.44 | F102: 1.46 | G102: 5.11 | H102: 17.4 | I102: =Tableau5[[#This Row],[Prod Solaire /KWH Maison]]+Tableau5[[#This Row],[Prod Solaire /KWH Cab]] -> 22.51
A103: Samedi | B103: 45759 | C103: 4.38 | D103: =Tableau5[[#This Row],[Total €/J]]-Tableau5[[#This Row],[Abonnement €]] -> 1.17 | E103: 0.44 | F103: 1.61 | G103: 5.26 | H103: 17.6 | I103: =Tableau5[[#This Row],[Prod Solaire /KWH Maison]]+Tableau5[[#This Row],[Prod Solaire /KWH Cab]] -> 22.86
A104: Dimanche | B104: 45760 | C104: 6.35 | D104: =Tableau5[[#This Row],[Total €/J]]-Tableau5[[#This Row],[Abonnement €]] -> 1.91 | E104: 0.44 | F104: 2.35 | G104: 2.04 | H104: 5.21 | I104: =Tableau5[[#This Row],[Prod Solaire /KWH Maison]]+Tableau5[[#This Row],[Prod Solaire /KWH Cab]] -> 7.25
A105: Lundi | B105: 45761 | C105: 5.37 | D105: =Tableau5[[#This Row],[Total €/J]]-Tableau5[[#This Row],[Abonnement €]] -> 1.35 | E105: 0.44 | F105: 1.79 | G105: 3.81 | H105: 12.6 | I105: =Tableau5[[#This Row],[Prod Solaire /KWH Maison]]+Tableau5[[#This Row],[Prod Solaire /KWH Cab]] -> 16.41
A106: Mardi | B106: 45762 | C106: 3.97 | D106: =Tableau5[[#This Row],[Total €/J]]-Tableau5[[#This Row],[Abonnement €]] -> 1.02 | E106: 0.44 | F106: 1.46 | G106: 1.46 | H106: 4.04 | I106: =Tableau5[[#This Row],[Prod Solaire /KWH Maison]]+Tableau5[[#This Row],[Prod Solaire /KWH Cab]] -> 5.5
A107: Mercredi | B107: 45763 | C107: 4.05 | D107: =Tableau5[[#This Row],[Total €/J]]-Tableau5[[#This Row],[Abonnement €]] -> 1.09 | E107: 0.44 | F107: 1.53 | G107: 3.62 | H107: 8.99 | I107: =Tableau5[[#This Row],[Prod Solaire /KWH Maison]]+Tableau5[[#This Row],[Prod Solaire /KWH Cab]] -> 12.61
A108: Jeudi | B108: 45764 | C108: 4.06 | D108: =Tableau5[[#This Row],[Total €/J]]-Tableau5[[#This Row],[Abonnement €]] -> 1.1 | E108: 0.44 | F108: 1.54 | G108: 4.41 | H108: 11.5 | I108: =Tableau5[[#This Row],[Prod Solaire /KWH Maison]]+Tableau5[[#This Row],[Prod Solaire /KWH Cab]] -> 15.91
A109: Vendredi | B109: 45765 | C109: 3.69 | D109: =Tableau5[[#This Row],[Total €/J]]-Tableau5[[#This Row],[Abonnement €]] -> 0.87 | E109: 0.44 | F109: 1.31 | G109: 6.53 | H109: 19.8 | I109: =Tableau5[[#This Row],[Prod Solaire /KWH Maison]]+Tableau5[[#This Row],[Prod Solaire /KWH Cab]] -> 26.33
A110: Samedi | B110: 45766 | C110: 5.89 | D110: =Tableau5[[#This Row],[Total €/J]]-Tableau5[[#This Row],[Abonnement €]] -> 1.61 | E110: 0.44 | F110: 2.05 | G110: 1.61 | H110: 5.88 | I110: =Tableau5[[#This Row],[Prod Solaire /KWH Maison]]+Tableau5[[#This Row],[Prod Solaire /KWH Cab]] -> 7.49
A111: Dimanche | B111: 45767 | C111: 2.45 | D111: =Tableau5[[#This Row],[Total €/J]]-Tableau5[[#This Row],[Abonnement €]] -> 0.66 | E111: 0.44 | F111: 1.1 | G111: 5.52 | H111: 18.4 | I111: =Tableau5[[#This Row],[Prod Solaire /KWH Maison]]+Tableau5[[#This Row],[Prod Solaire /KWH Cab]] -> 23.92
... A115: Jeudi | B115: 45771 | C115: 5.34 | D115: =Tableau5[[#This Row],[Total €/J]]-Tableau5[[#This Row],[Abonnement €]] -> 1.39 | E115: 0.44 | F115: 1.83 | G115: 4.61 | H115: 13.2 | I115: =Tableau5[[#This Row],[Prod Solaire /KWH Maison]]+Tableau5[[#This Row],[Prod Solaire /KWH Cab]] -> 17.81
A116: Vendredi | B116: 45772 | C116: 3.58 | D116: =Tableau5[[#This Row],[Total €/J]]-Tableau5[[#This Row],[Abonnement €]] -> 0.79 | E116: 0.44 | F116: 1.23 | G116: 6.68 | H116: 20.1 | I116: =Tableau5[[#This Row],[Prod Solaire /KWH Maison]]+Tableau5[[#This Row],[Prod Solaire /KWH Cab]] -> 26.78 | J116: Activation picine 6h
A117: Samedi | B117: 45773 | C117: 5.22 | D117: =Tableau5[[#This Row],[Total €/J]]-Tableau5[[#This Row],[Abonnement €]] -> 1.42 | E117: 0.44 | F117: 1.86 | G117: 3.07 | H117: 8.14 | I117: =Tableau5[[#This Row],[Prod Solaire /KWH Maison]]+Tableau5[[#This Row],[Prod Solaire /KWH Cab]] -> 11.21
A118: Dimanche | B118: 45774 | C118: 4.46 | D118: =Tableau5[[#This Row],[Total €/J]]-Tableau5[[#This Row],[Abonnement €]] -> 1.29 | E118: 0.44 | F118: 1.73 | G118: 3.91 | H118: 8.92 | I118: =Tableau5[[#This Row],[Prod Solaire /KWH Maison]]+Tableau5[[#This Row],[Prod Solaire /KWH Cab]] -> 12.83
A119: Lundi | B119: 45775 | C119: 4.36 | D119: =Tableau5[[#This Row],[Total €/J]]-Tableau5[[#This Row],[Abonnement €]] -> 1.25 | E119: 0.44 | F119: 1.69 | G119: 5.43 | H119: 16.2 | I119: =Tableau5[[#This Row],[Prod Solaire /KWH Maison]]+Tableau5[[#This Row],[Prod Solaire /KWH Cab]] -> 21.63
A120: Mardi | B120: 45776 | C120: 3.39 | D120: =Tableau5[[#This Row],[Total €/J]]-Tableau5[[#This Row],[Abonnement €]] -> 0.95 | E120: 0.44 | F120: 1.39 | G120: 6.76 | H120: 20.3 | I120: =Tableau5[[#This Row],[Prod Solaire /KWH Maison]]+Tableau5[[#This Row],[Prod Solaire /KWH Cab]] -> 27.06 | J120: 7h
A121: Mercredi | B121: 45777 | C121: 5.05 | D121: =Tableau5[[#This Row],[Total €/J]]-Tableau5[[#This Row],[Abonnement €]] -> 1.34 | E121: 0.44 | F121: 1.78 | G121: 6.78 | H121: 20.4 | I121: =Tableau5[[#This Row],[Prod Solaire /KWH Maison]]+Tableau5[[#This Row],[Prod Solaire /KWH Cab]] -> 27.18
A122: Jeudi | B122: 45778 | C122: 4.83 | D122: =Tableau5[[#This Row],[Total €/J]]-Tableau5[[#This Row],[Abonnement €]] -> 1.06 | E122: 0.44 | F122: 1.5 | G122: 5.68 | H122: 18.5 | I122: =Tableau5[[#This Row],[Prod Solaire /KWH Maison]]+Tableau5[[#This Row],[Prod Solaire /KWH Cab]] -> 24.18
A123: Vendredi | B123: 45779 | C123: 3.76 | D123: =Tableau5[[#This Row],[Total €/J]]-Tableau5[[#This Row],[Abonnement €]] -> 0.7 | E123: 0.44 | F123: 1.14 | G123: 4.66 | H123: 14.5 | I123: =Tableau5[[#This Row],[Prod Solaire /KWH Maison]]+Tableau5[[#This Row],[Prod Solaire /KWH Cab]] -> 19.16
A124: Samedi | B124: 45780 | C124: 3.16 | D124: =Tableau5[[#This Row],[Total €/J]]-Tableau5[[#This Row],[Abonnement €]] -> 0.83 | E124: 0.44 | F124: 1.27 | G124: 5.31 | H124: 17.2 | I124: =Tableau5[[#This Row],[Prod Solaire /KWH Maison]]+Tableau5[[#This Row],[Prod Solaire /KWH Cab]] -> 22.51
A125: Dimanche | B125: 45781 | C125: 6.69 | D125: =Tableau5[[#This Row],[Total €/J]]-Tableau5[[#This Row],[Abonnement €]] -> 1.94 | E125: 0.44 | F125: 2.38 | G125: 1.52 | H125: 4.27 | I125: =Tableau5[[#This Row],[Prod Solaire /KWH Maison]]+Tableau5[[#This Row],[Prod Solaire /KWH Cab]] -> 5.79
A126: Lundi | B126: 45782 | C126: 4.94 | D126: =Tableau5[[#This Row],[Total €/J]]-Tableau5[[#This Row],[Abonnement €]] -> 1.32 | E126: 0.44 | F126: 1.76 | G126: 3.71 | H126: 9.62 | I126: =Tableau5[[#This Row],[Prod Solaire /KWH Maison]]+Tableau5[[#This Row],[Prod Solaire /KWH Cab]] -> 13.33
A127: Mardi | B127: 45783 | C127: 7.87 | D127: =Tableau5[[#This Row],[Total €/J]]-Tableau5[[#This Row],[Abonnement €]] -> 2.14 | E127: 0.44 | F127: 2.58 | G127: 1.79 | H127: 5.04 | I127: =Tableau5[[#This Row],[Prod Solaire /KWH Maison]]+Tableau5[[#This Row],[Prod Solaire /KWH Cab]] -> 6.83
A128: Mercredi | B128: 45784 | C128: 5.12 | D128: =Tableau5[[#This Row],[Total €/J]]-Tableau5[[#This Row],[Abonnement €]] -> 1.25 | E128: 0.44 | F128: 1.69 | G128: 3.41 | H128: 8.84 | I128: =Tableau5[[#This Row],[Prod Solaire /KWH Maison]]+Tableau5[[#This Row],[Prod Solaire /KWH Cab]] -> 12.25
A129: Jeudi | B129: 45785 | C129: 3.86 | D129: =Tableau5[[#This Row],[Total €/J]]-Tableau5[[#This Row],[Abonnement €]] -> 0.96 | E129: 0.44 | F129: 1.4 | G129: 6.03 | H129: 18.6 | I129: =Tableau5[[#This Row],[Prod Solaire /KWH Maison]]+Tableau5[[#This Row],[Prod Solaire /KWH Cab]] -> 24.63
A130: Vendredi | B130: 45786 | C130: 3.48 | D130: =Tableau5[[#This Row],[Total €/J]]-Tableau5[[#This Row],[Abonnement €]] -> 0.92 | E130: 0.44 | F130: 1.36 | G130: 4.91 | H130: 12.2 | I130: =Tableau5[[#This Row],[Prod Solaire /KWH Maison]]+Tableau5[[#This Row],[Prod Solaire /KWH Cab]] -> 17.11
A131: Samedi | B131: 45787 | C131: 2.09 | D131: =Tableau5[[#This Row],[Total €/J]]-Tableau5[[#This Row],[Abonnement €]] -> 0.48 | E131: 0.44 | F131: 0.92 | G131: 6.16 | H131: 18.3 | I131: =Tableau5[[#This Row],[Prod Solaire /KWH Maison]]+Tableau5[[#This Row],[Prod Solaire /KWH Cab]] -> 24.46
A132: Dimanche | B132: 45788 | C132: 9.84 | D132: =Tableau5[[#This Row],[Total €/J]]-Tableau5[[#This Row],[Abonnement €]] -> 2.91 | E132: 0.44 | F132: 3.35 | G132: 2.31 | H132: 6.08 | I132: =Tableau5[[#This Row],[Prod Solaire /KWH Maison]]+Tableau5[[#This Row],[Prod Solaire /KWH Cab]] -> 8.39
... A147: Lundi | B147: 45803 | C147: 2.71 | D147: =Tableau5[[#This Row],[Total €/J]]-Tableau5[[#This Row],[Abonnement €]] -> 0.68 | E147: 0.44 | F147: 1.12 | G147: 5.62 | H147: 16.9 | I147: =Tableau5[[#This Row],[Prod Solaire /KWH Maison]]+Tableau5[[#This Row],[Prod Solaire /KWH Cab]] -> 22.52
A148: Mardi | B148: 45804 | C148: 2.78 | D148: =Tableau5[[#This Row],[Total €/J]]-Tableau5[[#This Row],[Abonnement €]] -> 0.69 | E148: 0.44 | F148: 1.13 | G148: 6.98 | H148: 19.4 | I148: =Tableau5[[#This Row],[Prod Solaire /KWH Maison]]+Tableau5[[#This Row],[Prod Solaire /KWH Cab]] -> 26.38 | J148: 11h
A149: Mercredi | B149: 45805 | C149: 3.89 | D149: =Tableau5[[#This Row],[Total €/J]]-Tableau5[[#This Row],[Abonnement €]] -> 0.9 | E149: 0.44 | F149: 1.34 | G149: 6.44 | H149: 19.1 | I149: =Tableau5[[#This Row],[Prod Solaire /KWH Maison]]+Tableau5[[#This Row],[Prod Solaire /KWH Cab]] -> 25.54
A150: Jeudi | B150: 45806 | C150: 5.63 | D150: =Tableau5[[#This Row],[Total €/J]]-Tableau5[[#This Row],[Abonnement €]] -> 1.41 | E150: 0.44 | F150: 1.85 | G150: 7.03 | H150: 20.3 | I150: =Tableau5[[#This Row],[Prod Solaire /KWH Maison]]+Tableau5[[#This Row],[Prod Solaire /KWH Cab]] -> 27.33
A151: Vendredi | B151: 45807 | C151: 3.73 | D151: =Tableau5[[#This Row],[Total €/J]]-Tableau5[[#This Row],[Abonnement €]] -> 0.98 | E151: 0.44 | F151: 1.42 | G151: 6.93 | H151: 20.2 | I151: =Tableau5[[#This Row],[Prod Solaire /KWH Maison]]+Tableau5[[#This Row],[Prod Solaire /KWH Cab]] -> 27.13
A152: Samedi | B152: 45808 | C152: 4.62 | D152: =Tableau5[[#This Row],[Total €/J]]-Tableau5[[#This Row],[Abonnement €]] -> 1.32 | E152: 0.44 | F152: 1.76 | G152: 6.63 | H152: 18.4 | I152: =Tableau5[[#This Row],[Prod Solaire /KWH Maison]]+Tableau5[[#This Row],[Prod Solaire /KWH Cab]] -> 25.03
A153: Dimanche | B153: 45809 | C153: 7.18 | D153: =Tableau5[[#This Row],[Total €/J]]-Tableau5[[#This Row],[Abonnement €]] -> 2.1 | E153: 0.44 | F153: 2.54 | G153: 3.23 | H153: 9.12 | I153: =Tableau5[[#This Row],[Prod Solaire /KWH Maison]]+Tableau5[[#This Row],[Prod Solaire /KWH Cab]] -> 12.35
A154: Lundi | B154: 45810 | C154: 7.33 | D154: =Tableau5[[#This Row],[Total €/J]]-Tableau5[[#This Row],[Abonnement €]] -> 2.16 | E154: 0.44 | F154: 2.6 | G154: 2.18 | H154: 5.48 | I154: =Tableau5[[#This Row],[Prod Solaire /KWH Maison]]+Tableau5[[#This Row],[Prod Solaire /KWH Cab]] -> 7.66
A155: Mardi | B155: 45811 | C155: 2.88 | D155: =Tableau5[[#This Row],[Total €/J]]-Tableau5[[#This Row],[Abonnement €]] -> 0.73 | E155: 0.44 | F155: 1.17 | G155: 6.05 | H155: 17.6 | I155: =Tableau5[[#This Row],[Prod Solaire /KWH Maison]]+Tableau5[[#This Row],[Prod Solaire /KWH Cab]] -> 23.65
A156: Mercredi | B156: 45812 | C156: 7.21 | D156: =Tableau5[[#This Row],[Total €/J]]-Tableau5[[#This Row],[Abonnement €]] -> 1.9 | E156: 0.44 | F156: 2.34 | G156: 3.17 | H156: 7.38 | I156: =Tableau5[[#This Row],[Prod Solaire /KWH Maison]]+Tableau5[[#This Row],[Prod Solaire /KWH Cab]] -> 10.55
A157: Jeudi | B157: 45813 | C157: 4.55 | D157: =Tableau5[[#This Row],[Total €/J]]-Tableau5[[#This Row],[Abonnement €]] -> 1.14 | E157: 0.44 | F157: 1.58 | G157: 5.46 | H157: 14.6 | I157: =Tableau5[[#This Row],[Prod Solaire /KWH Maison]]+Tableau5[[#This Row],[Prod Solaire /KWH Cab]] -> 20.06
A158: Vendredi | B158: 45814 | C158: 3.58 | D158: =Tableau5[[#This Row],[Total €/J]]-Tableau5[[#This Row],[Abonnement €]] -> 0.86 | E158: 0.44 | F158: 1.3 | G158: 5.01 | H158: 14.9 | I158: =Tableau5[[#This Row],[Prod Solaire /KWH Maison]]+Tableau5[[#This Row],[Prod Solaire /KWH Cab]] -> 19.91
A159: Samedi | B159: 45815 | C159: 12.45 | D159: =Tableau5[[#This Row],[Total €/J]]-Tableau5[[#This Row],[Abonnement €]] -> 3.63 | E159: 0.44 | F159: 4.07 | G159: 3.03 | H159: 7.51 | I159: =Tableau5[[#This Row],[Prod Solaire /KWH Maison]]+Tableau5[[#This Row],[Prod Solaire /KWH Cab]] -> 10.54
A160: Dimanche | B160: 45816 | C160: 3.74 | D160: =Tableau5[[#This Row],[Total €/J]]-Tableau5[[#This Row],[Abonnement €]] -> 0.91 | E160: 0.44 | F160: 1.35 | G160: 5.61 | H160: 13.7 | I160: =Tableau5[[#This Row],[Prod Solaire /KWH Maison]]+Tableau5[[#This Row],[Prod Solaire /KWH Cab]] -> 19.31
A161: Lundi | B161: 45817 | C161: 3.85 | D161: =Tableau5[[#This Row],[Total €/J]]-Tableau5[[#This Row],[Abonnement €]] -> 1 | E161: 0.44 | F161: 1.44 | G161: 6.84 | H161: 20.1 | I161: =Tableau5[[#This Row],[Prod Solaire /KWH Maison]]+Tableau5[[#This Row],[Prod Solaire /KWH Cab]] -> 26.94
A162: Mardi | B162: 45818 | C162: 2.75 | D162: =Tableau5[[#This Row],[Total €/J]]-Tableau5[[#This Row],[Abonnement €]] -> 0.71 | E162: 0.44 | F162: 1.15 | G162: 6.75 | H162: 19.7 | I162: =Tableau5[[#This Row],[Prod Solaire /KWH Maison]]+Tableau5[[#This Row],[Prod Solaire /KWH Cab]] -> 26.45 | J162: 12h
A163: Mercredi | B163: 45819 | C163: 2.98 | D163: =Tableau5[[#This Row],[Total €/J]]-Tableau5[[#This Row],[Abonnement €]] -> 0.71 | E163: 0.44 | F163: 1.15 | G163: 6.18 | H163: 19.2 | I163: =Tableau5[[#This Row],[Prod Solaire /KWH Maison]]+Tableau5[[#This Row],[Prod Solaire /KWH Cab]] -> 25.38
A164: Jeudi | B164: 45820 | C164: 3.23 | D164: =Tableau5[[#This Row],[Total €/J]]-Tableau5[[#This Row],[Abonnement €]] -> 0.81 | E164: 0.44 | F164: 1.25 | G164: 6.69 | H164: 19.3 | I164: =Tableau5[[#This Row],[Prod Solaire /KWH Maison]]+Tableau5[[#This Row],[Prod Solaire /KWH Cab]] -> 25.99
A165: Vendredi | B165: 45821 | C165: 5.33 | D165: =Tableau5[[#This Row],[Total €/J]]-Tableau5[[#This Row],[Abonnement €]] -> 1.41 | E165: 0.44 | F165: 1.85 | G165: 6.78 | H165: 19.8 | I165: =Tableau5[[#This Row],[Prod Solaire /KWH Maison]]+Tableau5[[#This Row],[Prod Solaire /KWH Cab]] -> 26.58 | J165: 24h
A166: Samedi | B166: 45822 | C166: 12.95 | D166: =Tableau5[[#This Row],[Total €/J]]-Tableau5[[#This Row],[Abonnement €]] -> 3.19 | E166: 0.44 | F166: 3.63 | G166: 5.66 | H166: 16.2 | I166: =Tableau5[[#This Row],[Prod Solaire /KWH Maison]]+Tableau5[[#This Row],[Prod Solaire /KWH Cab]] -> 21.86
A167: Dimanche | B167: 45823 | C167: 14.27 | D167: =Tableau5[[#This Row],[Total €/J]]-Tableau5[[#This Row],[Abonnement €]] -> 3.61 | E167: 0.44 | F167: 4.05 | G167: 1.29 | H167: 3.58 | I167: =Tableau5[[#This Row],[Prod Solaire /KWH Maison]]+Tableau5[[#This Row],[Prod Solaire /KWH Cab]] -> 4.87 | J167: 12h
A168: Lundi | B168: 45824 | C168: 4.06 | D168: =Tableau5[[#This Row],[Total €/J]]-Tableau5[[#This Row],[Abonnement €]] -> 0.99 | E168: 0.44 | F168: 1.43 | G168: 7.01 | H168: 19.9 | I168: =Tableau5[[#This Row],[Prod Solaire /KWH Maison]]+Tableau5[[#This Row],[Prod Solaire /KWH Cab]] -> 26.91
A169: Mardi | B169: 45825 | C169: 3.01 | D169: =Tableau5[[#This Row],[Total €/J]]-Tableau5[[#This Row],[Abonnement €]] -> 0.84 | E169: 0.44 | F169: 1.28 | G169: 7.03 | H169: 20.6 | I169: =Tableau5[[#This Row],[Prod Solaire /KWH Maison]]+Tableau5[[#This Row],[Prod Solaire /KWH Cab]] -> 27.63
A170: Mercredi | B170: 45826 | C170: 4.55 | D170: =Tableau5[[#This Row],[Total €/J]]-Tableau5[[#This Row],[Abonnement €]] -> 1.26 | E170: 0.44 | F170: 1.7 | G170: 6.96 | H170: 20.2 | I170: =Tableau5[[#This Row],[Prod Solaire /KWH Maison]]+Tableau5[[#This Row],[Prod Solaire /KWH Cab]] -> 27.16
A171: Jeudi | B171: 45827 | C171: 3.8 | D171: =Tableau5[[#This Row],[Total €/J]]-Tableau5[[#This Row],[Abonnement €]] -> 0.96 | E171: 0.44 | F171: 1.4 | G171: 6.69 | H171: 19.5 | I171: =Tableau5[[#This Row],[Prod Solaire /KWH Maison]]+Tableau5[[#This Row],[Prod Solaire /KWH Cab]] -> 26.19
A172: Vendredi | B172: 45828 | C172: 4.14 | D172: =Tableau5[[#This Row],[Total €/J]]-Tableau5[[#This Row],[Abonnement €]] -> 1.1 | E172: 0.44 | F172: 1.54 | G172: 6.73 | H172: 19.6 | I172: =Tableau5[[#This Row],[Prod Solaire /KWH Maison]]+Tableau5[[#This Row],[Prod Solaire /KWH Cab]] -> 26.33
A173: Samedi | B173: 45829 | C173: 7.59 | D173: =Tableau5[[#This Row],[Total €/J]]-Tableau5[[#This Row],[Abonnement €]] -> 1.84 | E173: 0.44 | F173: 2.28 | G173: 6.71 | H173: 19.5 | I173: =Tableau5[[#This Row],[Prod Solaire /KWH Maison]]+Tableau5[[#This Row],[Prod Solaire /KWH Cab]] -> 26.21
A174: Dimanche | B174: 45830 | C174: 6.52 | D174: =Tableau5[[#This Row],[Total €/J]]-Tableau5[[#This Row],[Abonnement €]] -> 1.76 | E174: 0.44 | F174: 2.2 | G174: 5.13 | H174: 12.8 | I174: =Tableau5[[#This Row],[Prod Solaire /KWH Maison]]+Tableau5[[#This Row],[Prod Solaire /KWH Cab]] -> 17.93
A175: Lundi | B175: 45831 | C175: 4.95 | D175: =Tableau5[[#This Row],[Total €/J]]-Tableau5[[#This Row],[Abonnement €]] -> 1.33 | E175: 0.44 | F175: 1.77 | G175: 6.11 | H175: 15 | I175: =Tableau5[[#This Row],[Prod Solaire /KWH Maison]]+Tableau5[[#This Row],[Prod Solaire /KWH Cab]] -> 21.11
A176: Mardi | B176: 45832 | C176: 2.91 | D176: =Tableau5[[#This Row],[Total €/J]]-Tableau5[[#This Row],[Abonnement €]] -> 0.71 | E176: 0.44 | F176: 1.15 | G176: 6.57 | H176: 19.1 | I176: =Tableau5[[#This Row],[Prod Solaire /KWH Maison]]+Tableau5[[#This Row],[Prod Solaire /KWH Cab]] -> 25.67
A177: Mercredi | B177: 45833 | C177: 6.65 | D177: =Tableau5[[#This Row],[Total €/J]]-Tableau5[[#This Row],[Abonnement €]] -> 1.91 | E177: 0.44 | F177: 2.35 | G177: 5.04 | H177: 16.6 | I177: =Tableau5[[#This Row],[Prod Solaire /KWH Maison]]+Tableau5[[#This Row],[Prod Solaire /KWH Cab]] -> 21.64
A178: Jeudi | B178: 45834 | C178: 3.67 | D178: =Tableau5[[#This Row],[Total €/J]]-Tableau5[[#This Row],[Abonnement €]] -> 1.03 | E178: 0.44 | F178: 1.47 | G178: 5.34 | H178: 14.7 | I178: =Tableau5[[#This Row],[Prod Solaire /KWH Maison]]+Tableau5[[#This Row],[Prod Solaire /KWH Cab]] -> 20.04
A179: Vendredi | B179: 45835 | C179: 2.41 | D179: =Tableau5[[#This Row],[Total €/J]]-Tableau5[[#This Row],[Abonnement €]] -> 0.62 | E179: 0.44 | F179: 1.06 | G179: 7.14 | H179: 19.7 | I179: =Tableau5[[#This Row],[Prod Solaire /KWH Maison]]+Tableau5[[#This Row],[Prod Solaire /KWH Cab]] -> 26.84
... A246: Mardi | B246: 45902 | C246: 3.76 | D246: =Tableau5[[#This Row],[Total €/J]]-Tableau5[[#This Row],[Abonnement €]] -> 1.14 | E246: 0.44 | F246: 1.58 | G246: 4.17 | H246: 14.2 | I246: =Tableau5[[#This Row],[Prod Solaire /KWH Maison]]+Tableau5[[#This Row],[Prod Solaire /KWH Cab]] -> 18.37
A247: Mercredi | B247: 45903 | C247: 3.75 | D247: =Tableau5[[#This Row],[Total €/J]]-Tableau5[[#This Row],[Abonnement €]] -> 0.96 | E247: 0.44 | F247: 1.4 | G247: 5.46 | H247: 17.8 | I247: =Tableau5[[#This Row],[Prod Solaire /KWH Maison]]+Tableau5[[#This Row],[Prod Solaire /KWH Cab]] -> 23.26 | J247: 10h
A248: Jeudi | B248: 45904 | C248: 5.4 | D248: =Tableau5[[#This Row],[Total €/J]]-Tableau5[[#This Row],[Abonnement €]] -> 1.48 | E248: 0.44 | F248: 1.92 | G248: 2.25 | H248: 5.76 | I248: =Tableau5[[#This Row],[Prod Solaire /KWH Maison]]+Tableau5[[#This Row],[Prod Solaire /KWH Cab]] -> 8.01
A249: Vendredi | B249: 45905 | C249: 4.66 | D249: =Tableau5[[#This Row],[Total €/J]]-Tableau5[[#This Row],[Abonnement €]] -> 1.3 | E249: 0.44 | F249: 1.74 | G249: 5.66 | H249: 15 | I249: =Tableau5[[#This Row],[Prod Solaire /KWH Maison]]+Tableau5[[#This Row],[Prod Solaire /KWH Cab]] -> 20.66
A250: Samedi | B250: 45906 | C250: 4.9 | D250: =Tableau5[[#This Row],[Total €/J]]-Tableau5[[#This Row],[Abonnement €]] -> 1.4 | E250: 0.44 | F250: 1.84 | G250: 5.49 | H250: 17.6 | I250: =Tableau5[[#This Row],[Prod Solaire /KWH Maison]]+Tableau5[[#This Row],[Prod Solaire /KWH Cab]] -> 23.09 | J250: 6h
A251: Dimanche | B251: 45907 | C251: 2.99 | D251: =Tableau5[[#This Row],[Total €/J]]-Tableau5[[#This Row],[Abonnement €]] -> 0.89 | E251: 0.44 | F251: 1.33 | G251: 4.57 | H251: 15.6 | I251: =Tableau5[[#This Row],[Prod Solaire /KWH Maison]]+Tableau5[[#This Row],[Prod Solaire /KWH Cab]] -> 20.17
A252: Lundi | B252: 45908 | C252: 3.7 | D252: =Tableau5[[#This Row],[Total €/J]]-Tableau5[[#This Row],[Abonnement €]] -> 1.1 | E252: 0.44 | F252: 1.54 | G252: 2.17 | H252: 6.12 | I252: =Tableau5[[#This Row],[Prod Solaire /KWH Maison]]+Tableau5[[#This Row],[Prod Solaire /KWH Cab]] -> 8.29
A253: Mardi | B253: 45909 | C253: 5.95 | D253: =Tableau5[[#This Row],[Total €/J]]-Tableau5[[#This Row],[Abonnement €]] -> 1.65 | E253: 0.44 | F253: 2.09 | G253: 3.62 | H253: 9.3 | I253: =Tableau5[[#This Row],[Prod Solaire /KWH Maison]]+Tableau5[[#This Row],[Prod Solaire /KWH Cab]] -> 12.92
A254: Mercredi | B254: 45910 | C254: 4.27 | D254: =Tableau5[[#This Row],[Total €/J]]-Tableau5[[#This Row],[Abonnement €]] -> 1.13 | E254: 0.44 | F254: 1.57 | G254: 3.77 | H254: 12.7 | I254: =Tableau5[[#This Row],[Prod Solaire /KWH Maison]]+Tableau5[[#This Row],[Prod Solaire /KWH Cab]] -> 16.47
A255: Jeudi | B255: 45911 | C255: 4.08 | D255: =Tableau5[[#This Row],[Total €/J]]-Tableau5[[#This Row],[Abonnement €]] -> 1.17 | E255: 0.44 | F255: 1.61 | G255: 3.28 | H255: 9.39 | I255: =Tableau5[[#This Row],[Prod Solaire /KWH Maison]]+Tableau5[[#This Row],[Prod Solaire /KWH Cab]] -> 12.67
A256: Vendredi | B256: 45912 | C256: 4.46 | D256: =Tableau5[[#This Row],[Total €/J]]-Tableau5[[#This Row],[Abonnement €]] -> 1.22 | E256: 0.44 | F256: 1.66 | G256: 3.37 | H256: 9.35 | I256: =Tableau5[[#This Row],[Prod Solaire /KWH Maison]]+Tableau5[[#This Row],[Prod Solaire /KWH Cab]] -> 12.72
A257: Samedi | B257: 45913 | C257: 11.55 | D257: =Tableau5[[#This Row],[Total €/J]]-Tableau5[[#This Row],[Abonnement €]] -> 3.31 | E257: 0.44 | F257: 3.75 | G257: 1.92 | H257: 5.3 | I257: =Tableau5[[#This Row],[Prod Solaire /KWH Maison]]+Tableau5[[#This Row],[Prod Solaire /KWH Cab]] -> 7.22
A258: Dimanche | B258: 45914 | C258: 7.04 | D258: =Tableau5[[#This Row],[Total €/J]]-Tableau5[[#This Row],[Abonnement €]] -> 2 | E258: 0.44 | F258: 2.44 | G258: 2.27 | H258: 7.49 | I258: =Tableau5[[#This Row],[Prod Solaire /KWH Maison]]+Tableau5[[#This Row],[Prod Solaire /KWH Cab]] -> 9.76
A259: Lundi | B259: 45915 | C259: 5.05 | D259: =Tableau5[[#This Row],[Total €/J]]-Tableau5[[#This Row],[Abonnement €]] -> 1.53 | E259: 0.44 | F259: 1.97 | G259: 3.33 | H259: 11.3 | I259: =Tableau5[[#This Row],[Prod Solaire /KWH Maison]]+Tableau5[[#This Row],[Prod Solaire /KWH Cab]] -> 14.63
A260: Mardi | B260: 45916 | C260: 3.54 | D260: =Tableau5[[#This Row],[Total €/J]]-Tableau5[[#This Row],[Abonnement €]] -> 1.02 | E260: 0.44 | F260: 1.46 | G260: 4.45 | H260: 14.7 | I260: =Tableau5[[#This Row],[Prod Solaire /KWH Maison]]+Tableau5[[#This Row],[Prod Solaire /KWH Cab]] -> 19.15
A261: Mercredi | B261: 45917 | C261: 2.82 | D261: =Tableau5[[#This Row],[Total €/J]]-Tableau5[[#This Row],[Abonnement €]] -> 0.79 | E261: 0.44 | F261: 1.23 | G261: 4.82 | H261: 16.4 | I261: =Tableau5[[#This Row],[Prod Solaire /KWH Maison]]+Tableau5[[#This Row],[Prod Solaire /KWH Cab]] -> 21.22
A262: Jeudi | B262: 45918 | C262: 3.95 | D262: =Tableau5[[#This Row],[Total €/J]]-Tableau5[[#This Row],[Abonnement €]] -> 1.19 | E262: 0.44 | F262: 1.63 | G262: 5.07 | H262: 16.8 | I262: =Tableau5[[#This Row],[Prod Solaire /KWH Maison]]+Tableau5[[#This Row],[Prod Solaire /KWH Cab]] -> 21.87
... A264: Samedi | B264: 45920 | C264: 4.74 | D264: =Tableau5[[#This Row],[Total €/J]]-Tableau5[[#This Row],[Abonnement €]] -> 1.35 | E264: 0.44 | F264: 1.79 | G264: 3.66 | H264: 13.5 | I264: =Tableau5[[#This Row],[Prod Solaire /KWH Maison]]+Tableau5[[#This Row],[Prod Solaire /KWH Cab]] -> 17.16
A265: Dimanche | B265: 45921 | C265: 5.73 | D265: =Tableau5[[#This Row],[Total €/J]]-Tableau5[[#This Row],[Abonnement €]] -> 1.66 | E265: 0.44 | F265: 2.1 | G265: 0.87 | H265: 2.4 | I265: =Tableau5[[#This Row],[Prod Solaire /KWH Maison]]+Tableau5[[#This Row],[Prod Solaire /KWH Cab]] -> 3.27 | J265: 4h
A266: Lundi | B266: 45922 | C266: 6.64 | D266: =Tableau5[[#This Row],[Total €/J]]-Tableau5[[#This Row],[Abonnement €]] -> 1.8 | E266: 0.44 | F266: 2.24 | G266: 2.93 | H266: 7.96 | I266: =Tableau5[[#This Row],[Prod Solaire /KWH Maison]]+Tableau5[[#This Row],[Prod Solaire /KWH Cab]] -> 10.89
A267: Mardi | B267: 45923 | C267: 8.43 | D267: =Tableau5[[#This Row],[Total €/J]]-Tableau5[[#This Row],[Abonnement €]] -> 2.47 | E267: 0.44 | F267: 2.91 | G267: 1.56 | H267: 4.23 | I267: =Tableau5[[#This Row],[Prod Solaire /KWH Maison]]+Tableau5[[#This Row],[Prod Solaire /KWH Cab]] -> 5.79
A268: Mercredi | B268: 45924 | C268: 5.61 | D268: =Tableau5[[#This Row],[Total €/J]]-Tableau5[[#This Row],[Abonnement €]] -> 1.55 | E268: 0.44 | F268: 1.99 | G268: 1.29 | H268: 3.47 | I268: =Tableau5[[#This Row],[Prod Solaire /KWH Maison]]+Tableau5[[#This Row],[Prod Solaire /KWH Cab]] -> 4.76
...

Sheet 2024
A2: Jour | B2: Date | C2: KWH | D2: Conso € | E2: Abonnement € | F2: Total €/J | G2: Production Solaire /KWH | H2: Colonne1
A3: Lundi | B3: 45292 | C3: 17.49 | D3: =Tableau13[[#This Row],[Total €/J]]-Tableau13[[#This Row],[Abonnement €]] -> 3.6 | E3: 0.4 | F3: 4 | G3: 1
A4: Mardi | B4: 45293 | C4: 12.73 | D4: =Tableau13[[#This Row],[Total €/J]]-Tableau13[[#This Row],[Abonnement €]] -> 2.56 | E4: 0.4 | F4: 2.96 | G4: 0.86
A5: Mercredi | B5: 45294 | C5: 13.78 | D5: =Tableau13[[#This Row],[Total €/J]]-Tableau13[[#This Row],[Abonnement €]] -> 2.88 | E5: 0.4 | F5: 3.28 | G5: 0.61
A6: jeudi | B6: 45295 | C6: 8.5 | D6: =Tableau13[[#This Row],[Total €/J]]-Tableau13[[#This Row],[Abonnement €]] -> 1.63 | E6: 0.4 | F6: 2.03 | G6: 1.67
A7: vendredi | B7: 45296 | C7: 12.08 | D7: =Tableau13[[#This Row],[Total €/J]]-Tableau13[[#This Row],[Abonnement €]] -> 2.46 | E7: 0.4 | F7: 2.86 | G7: 0.53
A8: Samedi | B8: 45297 | C8: 27.67 | D8: =Tableau13[[#This Row],[Total €/J]]-Tableau13[[#This Row],[Abonnement €]] -> 6.08 | E8: 0.4 | F8: 6.48 | G8: 0.6
A9: Dimanche | B9: 45298 | C9: 13.73 | D9: =Tableau13[[#This Row],[Total €/J]]-Tableau13[[#This Row],[Abonnement €]] -> 2.91 | E9: 0.4 | F9: 3.31 | G9: 0.5
A10: Lundi | B10: 45299 | C10: 10.27 | D10: =Tableau13[[#This Row],[Total €/J]]-Tableau13[[#This Row],[Abonnement €]] -> 2.01 | E10: 0.4 | F10: 2.41 | G10: 0.59
A11: Mardi | B11: 45300 | C11: 12.21 | D11: =Tableau13[[#This Row],[Total €/J]]-Tableau13[[#This Row],[Abonnement €]] -> 2.47 | E11: 0.4 | F11: 2.87 | G11: 1.88
A12: Mercredi | B12: 45301 | C12: 18.17 | D12: =Tableau13[[#This Row],[Total €/J]]-Tableau13[[#This Row],[Abonnement €]] -> 3.52 | E12: 0.4 | F12: 3.92 | G12: 0.8
A13: Jeudi | B13: 45302 | C13: 14.64 | D13: =Tableau13[[#This Row],[Total €/J]]-Tableau13[[#This Row],[Abonnement €]] -> 2.98 | E13: 0.4 | F13: 3.38 | G13: 0.13
A14: Vendredi | B14: 45303 | C14: 15.88 | D14: =Tableau13[[#This Row],[Total €/J]]-Tableau13[[#This Row],[Abonnement €]] -> 3.28 | E14: 0.4 | F14: 3.68 | G14: 0.29
... A103: Mercredi | B103: 45392 | C103: 7.93 | D103: =Tableau13[[#This Row],[Total €/J]]-Tableau13[[#This Row],[Abonnement €]] -> 1.82 | E103: 0.4 | F103: 2.22 | G103: 4.92
A104: Jeudi | B104: 45393 | C104: 6.72 | D104: =Tableau13[[#This Row],[Total €/J]]-Tableau13[[#This Row],[Abonnement €]] -> 1.57 | E104: 0.4 | F104: 1.97 | G104: 6 | H104: Activation picine 8h
A105: Vendredi | B105: 45394 | C105: 9.89 | D105: =Tableau13[[#This Row],[Total €/J]]-Tableau13[[#This Row],[Abonnement €]] -> 2.39 | E105: 0.4 | F105: 2.79 | G105: 6.24 | H105: 9h
A106: Samedi | B106: 45395 | C106: 5.74 | D106: =Tableau13[[#This Row],[Total €/J]]-Tableau13[[#This Row],[Abonnement €]] -> 1.37 | E106: 0.4 | F106: 1.77 | G106: 6.14
A107: Dimanche | B107: 45396 | C107: 10.53 | D107: =Tableau13[[#This Row],[Total €/J]]-Tableau13[[#This Row],[Abonnement €]] -> 2.92 | E107: 0.4 | F107: 3.32 | G107: 5.98
A108: Lundi | B108: 45397 | C108: 9.5 | D108: =Tableau13[[#This Row],[Total €/J]]-Tableau13[[#This Row],[Abonnement €]] -> 2.5 | E108: 0.4 | F108: 2.9 | G108: 2.22
A109: Mardi | B109: 45398 | C109: 8.13 | D109: =Tableau13[[#This Row],[Total €/J]]-Tableau13[[#This Row],[Abonnement €]] -> 2.03 | E109: 0.4 | F109: 2.43 | G109: 4.74
A110: Mercredi | B110: 45399 | C110: 10.65 | D110: =Tableau13[[#This Row],[Total €/J]]-Tableau13[[#This Row],[Abonnement €]] -> 2.77 | E110: 0.4 | F110: 3.17 | G110: 3.52 | H110: 7h
A111: Jeudi | B111: 45400 | C111: 5.96 | D111: =Tableau13[[#This Row],[Total €/J]]-Tableau13[[#This Row],[Abonnement €]] -> 1.52 | E111: 0.4 | F111: 1.92 | G111: 4.71
A112: Vendredi | B112: 45401 | C112: 7.54 | D112: =Tableau13[[#This Row],[Total €/J]]-Tableau13[[#This Row],[Abonnement €]] -> 1.87 | E112: 0.4 | F112: 2.27 | G112: 6.7
A113: Samedi | B113: 45402 | C113: 7.48 | D113: =Tableau13[[#This Row],[Total €/J]]-Tableau13[[#This Row],[Abonnement €]] -> 1.85 | E113: 0.4 | F113: 2.25 | G113: 6.91
A114: Dimanche | B114: 45403 | C114: 8.19 | D114: =Tableau13[[#This Row],[Total €/J]]-Tableau13[[#This Row],[Abonnement €]] -> 2.21 | E114: 0.4 | F114: 2.61 | G114: 6.71
A115: Lundi | B115: 45404 | C115: 8.88 | D115: =Tableau13[[#This Row],[Total €/J]]-Tableau13[[#This Row],[Abonnement €]] -> 2.21 | E115: 0.4 | F115: 2.61 | G115: 5.16
A116: Mardi | B116: 45405 | C116: 8 | D116: =Tableau13[[#This Row],[Total €/J]]-Tableau13[[#This Row],[Abonnement €]] -> 1.93 | E116: 0.4 | F116: 2.33 | G116: 5.46
A117: Mercredi | B117: 45406 | C117: 13.51 | D117: =Tableau13[[#This Row],[Total €/J]]-Tableau13[[#This Row],[Abonnement €]] -> 3.52 | E117: 0.4 | F117: 3.92 | G117: 1.34
A118: Jeudi | B118: 45407 | C118: 10.98 | D118: =Tableau13[[#This Row],[Total €/J]]-Tableau13[[#This Row],[Abonnement €]] -> 2.82 | E118: 0.4 | F118: 3.22 | G118: 3.74
A119: Vendredi | B119: 45408 | C119: 10.3 | D119: =Tableau13[[#This Row],[Total €/J]]-Tableau13[[#This Row],[Abonnement €]] -> 2.63 | E119: 0.4 | F119: 3.03 | G119: 5.25
A120: Samedi | B120: 45409 | C120: 9.53 | D120: =Tableau13[[#This Row],[Total €/J]]-Tableau13[[#This Row],[Abonnement €]] -> 2.47 | E120: 0.4 | F120: 2.87 | G120: 3.58
A121: Dimanche | B121: 45410 | C121: 11.34 | D121: =Tableau13[[#This Row],[Total €/J]]-Tableau13[[#This Row],[Abonnement €]] -> 3.06 | E121: 0.4 | F121: 3.46 | G121: 3.22
A122: Lundi | B122: 45411 | C122: 10.64 | D122: =Tableau13[[#This Row],[Total €/J]]-Tableau13[[#This Row],[Abonnement €]] -> 2.86 | E122: 0.4 | F122: 3.26 | G122: 0.96
... A152: Mercredi | B152: 45441 | C152: 8.13 | D152: =Tableau13[[#This Row],[Total €/J]]-Tableau13[[#This Row],[Abonnement €]] -> 2.11 | E152: 0.4 | F152: 2.51 | G152: 4.39
A153: Jeudi | B153: 45442 | C153: 6.48 | D153: =Tableau13[[#This Row],[Total €/J]]-Tableau13[[#This Row],[Abonnement €]] -> 1.67 | E153: 0.4 | F153: 2.07 | G153: 4.71 | H153: 8H30
A154: Vendredi | B154: 45443 | C154: 9.31 | D154: =Tableau13[[#This Row],[Total €/J]]-Tableau13[[#This Row],[Abonnement €]] -> 2.31 | E154: 0.4 | F154: 2.71 | G154: 4.08
A155: Samedi | B155: 45444 | C155: 21.24 | D155: =Tableau13[[#This Row],[Total €/J]]-Tableau13[[#This Row],[Abonnement €]] -> 5.94 | E155: 0.4 | F155: 6.34 | G155: 4.84
A156: Dimanche | B156: 45445 | C156: 12.41 | D156: =Tableau13[[#This Row],[Total €/J]]-Tableau13[[#This Row],[Abonnement €]] -> 3.27 | E156: 0.4 | F156: 3.67 | G156: 4.51
A157: Lundi | B157: 45446 | C157: 8.1 | D157: =Tableau13[[#This Row],[Total €/J]]-Tableau13[[#This Row],[Abonnement €]] -> 2.07 | E157: 0.4 | F157: 2.47 | G157: 6.6
A158: Mardi | B158: 45447 | C158: 6.84 | D158: =Tableau13[[#This Row],[Total €/J]]-Tableau13[[#This Row],[Abonnement €]] -> 1.85 | E158: 0.4 | F158: 2.25 | G158: 6.89 | H158: 10h
A159: Mercredi | B159: 45448 | C159: 6.69 | D159: =Tableau13[[#This Row],[Total €/J]]-Tableau13[[#This Row],[Abonnement €]] -> 1.75 | E159: 0.4 | F159: 2.15 | G159: 7.05
A160: Jeudi | B160: 45449 | C160: 6.87 | D160: =Tableau13[[#This Row],[Total €/J]]-Tableau13[[#This Row],[Abonnement €]] -> 1.85 | E160: 0.4 | F160: 2.25 | G160: 6.2
A161: Vendredi | B161: 45450 | C161: 8.31 | D161: =Tableau13[[#This Row],[Total €/J]]-Tableau13[[#This Row],[Abonnement €]] -> 2.16 | E161: 0.4 | F161: 2.56 | G161: 4
A162: Samedi | B162: 45451 | C162: 9.66 | D162: =Tableau13[[#This Row],[Total €/J]]-Tableau13[[#This Row],[Abonnement €]] -> 2.54 | E162: 0.4 | F162: 2.94 | G162: 5.31
A163: Dimanche | B163: 45452 | C163: 12.63 | D163: =Tableau13[[#This Row],[Total €/J]]-Tableau13[[#This Row],[Abonnement €]] -> 3.51 | E163: 0.4 | F163: 3.91 | G163: 2.82
A164: Lundi | B164: 45453 | C164: 9 | D164: =Tableau13[[#This Row],[Total €/J]]-Tableau13[[#This Row],[Abonnement €]] -> 2.42 | E164: 0.4 | F164: 2.82 | G164: 4.79
A165: Mardi | B165: 45454 | C165: 10.07 | D165: =Tableau13[[#This Row],[Total €/J]]-Tableau13[[#This Row],[Abonnement €]] -> 2.67 | E165: 0.4 | F165: 3.07 | G165: 3.47
A166: Mercredi | B166: 45455 | C166: 12.78 | D166: =Tableau13[[#This Row],[Total €/J]]-Tableau13[[#This Row],[Abonnement €]] -> 3.51 | E166: 0.4 | F166: 3.91 | G166: 5.43
A167: Jeudi | B167: 45456 | C167: 7.1 | D167: =Tableau13[[#This Row],[Total €/J]]-Tableau13[[#This Row],[Abonnement €]] -> 1.68 | E167: 0.4 | F167: 2.08 | G167: 7.42
A168: Vendredi | B168: 45457 | C168: 5.48 | D168: =Tableau13[[#This Row],[Total €/J]]-Tableau13[[#This Row],[Abonnement €]] -> 1.44 | E168: 0.4 | F168: 1.84 | G168: 4.83
A169: Samedi | B169: 45458 | C169: 12.01 | D169: =Tableau13[[#This Row],[Total €/J]]-Tableau13[[#This Row],[Abonnement €]] -> 3.29 | E169: 0.4 | F169: 3.69 | G169: 4.85
A170: Dimanche | B170: 45459 | C170: 7.26 | D170: =Tableau13[[#This Row],[Total €/J]]-Tableau13[[#This Row],[Abonnement €]] -> 1.89 | E170: 0.4 | F170: 2.29 | G170: 7.28
... A179: Mardi | B179: 45468 | C179: 6.5 | D179: =Tableau13[[#This Row],[Total €/J]]-Tableau13[[#This Row],[Abonnement €]] -> 1.66 | E179: 0.4 | F179: 2.06 | G179: 7
A180: Mercredi | B180: 45469 | C180: 6.18 | D180: =Tableau13[[#This Row],[Total €/J]]-Tableau13[[#This Row],[Abonnement €]] -> 1.54 | E180: 0.4 | F180: 1.94 | G180: 7.18 | H180: 14h
A181: Jeudi | B181: 45470 | C181: 9.42 | D181: =Tableau13[[#This Row],[Total €/J]]-Tableau13[[#This Row],[Abonnement €]] -> 2.32 | E181: 0.4 | F181: 2.72 | G181: 5.53
A182: Vendredi | B182: 45471 | C182: 12.85 | D182: =Tableau13[[#This Row],[Total €/J]]-Tableau13[[#This Row],[Abonnement €]] -> 2.99 | E182: 0.4 | F182: 3.39 | G182: 5.87
A183: Samedi | B183: 45472 | C183: 14.81 | D183: =Tableau13[[#This Row],[Total €/J]]-Tableau13[[#This Row],[Abonnement €]] -> 4.04 | E183: 0.4 | F183: 4.44 | G183: 1.77
A184: Dimanche | B184: 45473 | C184: 10.01 | D184: =Tableau13[[#This Row],[Total €/J]]-Tableau13[[#This Row],[Abonnement €]] -> 2.7 | E184: 0.4 | F184: 3.1 | G184: 3.54
A185: Lundi | B185: 45474 | C185: 9.01 | D185: =Tableau13[[#This Row],[Total €/J]]-Tableau13[[#This Row],[Abonnement €]] -> 2.33 | E185: 0.4 | F185: 2.73 | G185: 5.23
A186: Mardi | B186: 45475 | C186: 11.93 | D186: =Tableau13[[#This Row],[Total €/J]]-Tableau13[[#This Row],[Abonnement €]] -> 3.26 | E186: 0.4 | F186: 3.66 | G186: 1.69
A187: Mercredi | B187: 45476 | C187: 7.83 | D187: =Tableau13[[#This Row],[Total €/J]]-Tableau13[[#This Row],[Abonnement €]] -> 2.13 | E187: 0.4 | F187: 2.53 | G187: 5.77
A188: Jeudi | B188: 45477 | C188: 10.13 | D188: =Tableau13[[#This Row],[Total €/J]]-Tableau13[[#This Row],[Abonnement €]] -> 2.72 | E188: 0.4 | F188: 3.12 | G188: 4.26
A189: Vendredi | B189: 45478 | C189: 9.05 | D189: =Tableau13[[#This Row],[Total €/J]]-Tableau13[[#This Row],[Abonnement €]] -> 2.37 | E189: 0.4 | F189: 2.77 | G189: 6.63
A190: Samedi | B190: 45479 | C190: 17.31 | D190: =Tableau13[[#This Row],[Total €/J]]-Tableau13[[#This Row],[Abonnement €]] -> 4.87 | E190: 0.4 | F190: 5.27 | G190: 1.3
A191: Dimanche | B191: 45480 | C191: 9.47 | D191: =Tableau13[[#This Row],[Total €/J]]-Tableau13[[#This Row],[Abonnement €]] -> 2.6 | E191: 0.4 | F191: 3 | G191: 7.57
A192: Lundi | B192: 45481 | C192: 8.43 | D192: =Tableau13[[#This Row],[Total €/J]]-Tableau13[[#This Row],[Abonnement €]] -> 2.12 | E192: 0.4 | F192: 2.52 | G192: 7.05
... A236: Mercredi | B236: 45525 | C236: 10.31 | D236: =Tableau13[[#This Row],[Total €/J]]-Tableau13[[#This Row],[Abonnement €]] -> 2.84 | E236: 0.4 | F236: 3.24 | G236: 6.54
A237: Jeudi | B237: 45526 | C237: 7.14 | D237: =Tableau13[[#This Row],[Total €/J]]-Tableau13[[#This Row],[Abonnement €]] -> 1.91 | E237: 0.4 | F237: 2.31 | G237: 6.32 | H237: 13h
A238: Vendredi | B238: 45527 | C238: 8.17 | D238: =Tableau13[[#This Row],[Total €/J]]-Tableau13[[#This Row],[Abonnement €]] -> 2.05 | E238: 0.4 | F238: 2.45 | G238: 5.99
A239: Samedi | B239: 45528 | C239: 11.15 | D239: =Tableau13[[#This Row],[Total €/J]]-Tableau13[[#This Row],[Abonnement €]] -> 3.08 | E239: 0.4 | F239: 3.48 | G239: 4.7
A240: Dimanche | B240: 45529 | C240: 8.59 | D240: =Tableau13[[#This Row],[Total €/J]]-Tableau13[[#This Row],[Abonnement €]] -> 2.25 | E240: 0.4 | F240: 2.65 | G240: 5.86
A241: Lundi | B241: 45530 | C241: 10.02 | D241: =Tableau13[[#This Row],[Total €/J]]-Tableau13[[#This Row],[Abonnement €]] -> 2.47 | E241: 0.4 | F241: 2.87 | G241: 6.36
A242: Mardi | B242: 45531 | C242: 7.37 | D242: =Tableau13[[#This Row],[Total €/J]]-Tableau13[[#This Row],[Abonnement €]] -> 1.99 | E242: 0.4 | F242: 2.39 | G242: 6.15
A243: Mercredi | B243: 45532 | C243: 6.93 | D243: =Tableau13[[#This Row],[Total €/J]]-Tableau13[[#This Row],[Abonnement €]] -> 1.8 | E243: 0.4 | F243: 2.2 | G243: 5.87
A244: Jeudi | B244: 45533 | C244: 8.39 | D244: =Tableau13[[#This Row],[Total €/J]]-Tableau13[[#This Row],[Abonnement €]] -> 2.06 | E244: 0.4 | F244: 2.46 | G244: 5.1
A245: Vendredi | B245: 45534 | C245: 8.81 | D245: =Tableau13[[#This Row],[Total €/J]]-Tableau13[[#This Row],[Abonnement €]] -> 2.26 | E245: 0.4 | F245: 2.66 | G245: 5.6
A246: Samedi | B246: 45535 | C246: 11.99 | D246: =Tableau13[[#This Row],[Total €/J]]-Tableau13[[#This Row],[Abonnement €]] -> 3.23 | E246: 0.4 | F246: 3.63 | G246: 5.31
A247: Dimanche | B247: 45536 | C247: 10.53 | D247: =Tableau13[[#This Row],[Total €/J]]-Tableau13[[#This Row],[Abonnement €]] -> 2.72 | E247: 0.4 | F247: 3.12 | G247: 2.95
A248: Lundi | B248: 45537 | C248: 7.06 | D248: =Tableau13[[#This Row],[Total €/J]]-Tableau13[[#This Row],[Abonnement €]] -> 1.91 | E248: 0.4 | F248: 2.31 | G248: 5.75
A249: Mardi | B249: 45538 | C249: 10.83 | D249: =Tableau13[[#This Row],[Total €/J]]-Tableau13[[#This Row],[Abonnement €]] -> 2.9 | E249: 0.4 | F249: 3.3 | G249: 2.52
A250: Mercredi | B250: 45539 | C250: 16.49 | D250: =Tableau13[[#This Row],[Total €/J]]-Tableau13[[#This Row],[Abonnement €]] -> 4.46 | E250: 0.4 | F250: 4.86 | G250: 0.74
A251: Jeudi | B251: 45540 | C251: 9.3 | D251: =Tableau13[[#This Row],[Total €/J]]-Tableau13[[#This Row],[Abonnement €]] -> 2.2 | E251: 0.4 | F251: 2.6 | G251: 4.38 | H251: 12H
A252: Vendredi | B252: 45541 | C252: 11.98 | D252: =Tableau13[[#This Row],[Total €/J]]-Tableau13[[#This Row],[Abonnement €]] -> 3.22 | E252: 0.4 | F252: 3.62 | G252: 2.74
A253: Samedi | B253: 45542 | C253: 18.74 | D253: =Tableau13[[#This Row],[Total €/J]]-Tableau13[[#This Row],[Abonnement €]] -> 5.29 | E253: 0.4 | F253: 5.69 | G253: 3.21
A254: Dimanche | B254: 45543 | C254: 10.13 | D254: =Tableau13[[#This Row],[Total €/J]]-Tableau13[[#This Row],[Abonnement €]] -> 2.79 | E254: 0.4 | F254: 3.19 | G254: 2.4
A255: Lundi | B255: 45544 | C255: 12.01 | D255: =Tableau13[[#This Row],[Total €/J]]-Tableau13[[#This Row],[Abonnement €]] -> 3.14 | E255: 0.4 | F255: 3.54 | G255: 2.02
A256: Mardi | B256: 45545 | C256: 8.06 | D256: =Tableau13[[#This Row],[Total €/J]]-Tableau13[[#This Row],[Abonnement €]] -> 2.21 | E256: 0.4 | F256: 2.61 | G256: 4.75
A257: Mercredi | B257: 45546 | C257: 12.55 | D257: =Tableau13[[#This Row],[Total €/J]]-Tableau13[[#This Row],[Abonnement €]] -> 3.24 | E257: 0.4 | F257: 3.64 | G257: 1.38
A258: Jeudi | B258: 45547 | C258: 10.15 | D258: =Tableau13[[#This Row],[Total €/J]]-Tableau13[[#This Row],[Abonnement €]] -> 2.73 | E258: 0.4 | F258: 3.13 | G258: 4.01
A259: Vendredi | B259: 45548 | C259: 6.58 | D259: =Tableau13[[#This Row],[Total €/J]]-Tableau13[[#This Row],[Abonnement €]] -> 1.66 | E259: 0.4 | F259: 2.06 | G259: 5.01 | H259: 10H
A260: Samedi | B260: 45549 | C260: 8.47 | D260: =Tableau13[[#This Row],[Total €/J]]-Tableau13[[#This Row],[Abonnement €]] -> 2.11 | E260: 0.4 | F260: 2.51 | G260: 5.85
A261: Dimanche | B261: 45550 | C261: 8.12 | D261: =Tableau13[[#This Row],[Total €/J]]-Tableau13[[#This Row],[Abonnement €]] -> 2.17 | E261: 0.4 | F261: 2.57 | G261: 5.85
A262: Lundi | B262: 45551 | C262: 9.07 | D262: =Tableau13[[#This Row],[Total €/J]]-Tableau13[[#This Row],[Abonnement €]] -> 2.25 | E262: 0.4 | F262: 2.65 | G262: 5.5
A263: Mardi | B263: 45552 | C263: 9.08 | D263: =Tableau13[[#This Row],[Total €/J]]-Tableau13[[#This Row],[Abonnement €]] -> 2.36 | E263: 0.4 | F263: 2.76 | G263: 2.77
A264: Mercredi | B264: 45553 | C264: 11.27 | D264: =Tableau13[[#This Row],[Total €/J]]-Tableau13[[#This Row],[Abonnement €]] -> 2.88 | E264: 0.4 | F264: 3.28 | G264: 4.93 | H264: 8H
A265: Jeudi | B265: 45554 | C265: 5.83 | D265: =Tableau13[[#This Row],[Total €/J]]-Tableau13[[#This Row],[Abonnement €]] -> 1.42 | E265: 0.4 | F265: 1.82 | G265: 5.32
A266: Vendredi | B266: 45555 | C266: 8.28 | D266: =Tableau13[[#This Row],[Total €/J]]-Tableau13[[#This Row],[Abonnement €]] -> 2.27 | E266: 0.4 | F266: 2.67 | G266: 2.3
A267: Samedi | B267: 45556 | C267: 12.58 | D267: =Tableau13[[#This Row],[Total €/J]]-Tableau13[[#This Row],[Abonnement €]] -> 3.43 | E267: 0.4 | F267: 3.83 | G267: 3.66
A268: Dimanche | B268: 45557 | C268: 8.49 | D268: =Tableau13[[#This Row],[Total €/J]]-Tableau13[[#This Row],[Abonnement €]] -> 2.33 | E268: 0.4 | F268: 2.73 | G268: 1.16
A269: Lundi | B269: 45558 | C269: 7 | D269: =Tableau13[[#This Row],[Total €/J]]-Tableau13[[#This Row],[Abonnement €]] -> 1.78 | E269: 0.4 | F269: 2.18 | G269: 3.35
...

Sheet 2023
A2: Jour | B2: Date | C2: KWH | D2: Conso € | E2: Abonnement € | F2: Total €/J | G2: Production Solaire /KWH
A3: Dimanche | B3: 44927 | C3: 13.49 | D3: =3.23-0.43 -> 2.8 | E3: 0.4 | F3: =D3+E3 -> 3.2
A4: Lundi | B4: 44928 | C4: 10.4 | D4: =2.58-0.43 -> 2.15 | E4: 0.4 | F4: =D4+E4 -> 2.55
A5: Mardi | B5: 44929 | C5: 13.45 | D5: =3.22-0.43 -> 2.79 | E5: 0.4 | F5: =D5+E5 -> 3.19
A6: Mercredi | B6: 44930 | C6: 11.75 | D6: =2.86-0.43 -> 2.43 | E6: 0.4 | F6: =D6+E6 -> 2.83
A7: Jeudi | B7: 44931 | C7: 12.88 | D7: =3.1-0.43 -> 2.67 | E7: 0.4 | F7: =D7+E7 -> 3.07
A8: Vendredi | B8: 44932 | C8: 10.7 | D8: =2.64-0.43 -> 2.21 | E8: 0.4 | F8: =D8+E8 -> 2.61
A9: Samedi | B9: 44933 | C9: 21.85 | D9: =4.99-0.43 -> 4.56 | E9: 0.4 | F9: =D9+E9 -> 4.96
A10: Dimanche | B10: 44934 | C10: 13.41 | D10: =3.21-0.43 -> 2.78 | E10: 0.4 | F10: =D10+E10 -> 3.18
A11: Lundi | B11: 44935 | C11: 12.5 | D11: =3.02-0.43 -> 2.59 | E11: 0.4 | F11: =D11+E11 -> 2.99
A12: Mardi | B12: 44936 | C12: 10.25 | D12: =2.55-0.43 -> 2.12 | E12: 0.4 | F12: =D12+E12 -> 2.52
A13: Mercredi | B13: 44937 | C13: 14.02 | D13: =Tableau1[[#This Row],[Total €/J]]-Tableau1[[#This Row],[Abonnement €]] -> 2.94 | E13: 0.4 | F13: 3.34
A14: Jeudi | B14: 44938 | C14: 12.45 | D14: =Tableau1[[#This Row],[Total €/J]]-Tableau1[[#This Row],[Abonnement €]] -> 2.61 | E14: 0.4 | F14: 3.01
A15: Vendredi | B15: 44939 | C15: 19.22 | D15: =Tableau1[[#This Row],[Total €/J]]-Tableau1[[#This Row],[Abonnement €]] -> 4.04 | E15: 0.4 | F15: 4.44
A16: Samedi | B16: 44940 | C16: 14.83 | D16: =Tableau1[[#This Row],[Total €/J]]-Tableau1[[#This Row],[Abonnement €]] -> 3.11 | E16: 0.4 | F16: 3.51
A17: Dimanche | B17: 44941 | C17: 19.21 | D17: =Tableau1[[#This Row],[Total €/J]]-Tableau1[[#This Row],[Abonnement €]] -> 4.04 | E17: 0.4 | F17: 4.44
A18: Lundi | B18: 44942 | C18: 21.48 | D18: =Tableau1[[#This Row],[Total €/J]]-Tableau1[[#This Row],[Abonnement €]] -> 4.51 | E18: 0.4 | F18: 4.91
A19: Mardi | B19: 44943 | C19: 15.35 | D19: =Tableau1[[#This Row],[Total €/J]]-Tableau1[[#This Row],[Abonnement €]] -> 3.22 | E19: 0.4 | F19: 3.62
A20: Mercredi | B20: 44944 | C20: 19.18 | D20: =Tableau1[[#This Row],[Total €/J]]-Tableau1[[#This Row],[Abonnement €]] -> 4.03 | E20: 0.4 | F20: 4.43
A21: Jeudi | B21: 44945 | C21: 19.3 | D21: =Tableau1[[#This Row],[Total €/J]]-Tableau1[[#This Row],[Abonnement €]] -> 4.05 | E21: 0.4 | F21: 4.45
A22: Vendredi | B22: 44946 | C22: 21.66 | D22: =Tableau1[[#This Row],[Total €/J]]-Tableau1[[#This Row],[Abonnement €]] -> 4.55 | E22: 0.4 | F22: 4.95
A23: Samedi | B23: 44947 | C23: 21.46 | D23: =Tableau1[[#This Row],[Total €/J]]-Tableau1[[#This Row],[Abonnement €]] -> 4.51 | E23: 0.4 | F23: 4.91
A24: Dimanche | B24: 44948 | C24: 20.15 | D24: =Tableau1[[#This Row],[Total €/J]]-Tableau1[[#This Row],[Abonnement €]] -> 4.23 | E24: 0.4 | F24: 4.63
... A102: Lundi | B102: 45026 | C102: 8.89 | D102: =Tableau1[[#This Row],[Total €/J]]-Tableau1[[#This Row],[Abonnement €]] -> 1.86 | E102: 0.4 | F102: 2.26
A103: Mardi | B103: 45027 | C103: 14.04 | D103: =Tableau1[[#This Row],[Total €/J]]-Tableau1[[#This Row],[Abonnement €]] -> 2.93 | E103: 0.4 | F103: 3.33 | H103: Activation picine 7h
A104: Mercredi | B104: 45028 | C104: 9.3 | D104: =Tableau1[[#This Row],[Total €/J]]-Tableau1[[#This Row],[Abonnement €]] -> 1.94 | E104: 0.4 | F104: 2.34
A105: Jeudi | B105: 45029 | C105: 10.09 | D105: =Tableau1[[#This Row],[Total €/J]]-Tableau1[[#This Row],[Abonnement €]] -> 2.11 | E105: 0.4 | F105: 2.51
A106: Vendredi | B106: 45030 | C106: 11.98 | D106: =Tableau1[[#This Row],[Total €/J]]-Tableau1[[#This Row],[Abonnement €]] -> 2.5 | E106: 0.4 | F106: 2.9
A107: Samedi | B107: 45031 | C107: 21.08 | D107: =Tableau1[[#This Row],[Total €/J]]-Tableau1[[#This Row],[Abonnement €]] -> 4.4 | E107: 0.4 | F107: 4.8
A108: Dimanche | B108: 45032 | C108: 12.67 | D108: =Tableau1[[#This Row],[Total €/J]]-Tableau1[[#This Row],[Abonnement €]] -> 2.64 | E108: 0.4 | F108: 3.04
A109: Lundi | B109: 45033 | C109: 11.41 | D109: =Tableau1[[#This Row],[Total €/J]]-Tableau1[[#This Row],[Abonnement €]] -> 2.38 | E109: 0.4 | F109: 2.78
A110: Mardi | B110: 45034 | C110: 13.68 | D110: =Tableau1[[#This Row],[Total €/J]]-Tableau1[[#This Row],[Abonnement €]] -> 2.9 | E110: 0.4 | F110: 3.3
A111: Mercredi | B111: 45035 | C111: 13.68 | D111: =Tableau1[[#This Row],[Total €/J]]-Tableau1[[#This Row],[Abonnement €]] -> 2.79 | E111: 0.4 | F111: 3.19
A112: Jeudi | B112: 45036 | C112: 10.3 | D112: =Tableau1[[#This Row],[Total €/J]]-Tableau1[[#This Row],[Abonnement €]] -> 2.13 | E112: 0.4 | F112: 2.53
A113: Vendredi | B113: 45037 | C113: 20.8 | D113: =Tableau1[[#This Row],[Total €/J]]-Tableau1[[#This Row],[Abonnement €]] -> 4.29 | E113: 0.4 | F113: 4.69 | H113: 11h
A114: Samedi | B114: 45038 | C114: 19.53 | D114: =Tableau1[[#This Row],[Total €/J]]-Tableau1[[#This Row],[Abonnement €]] -> 4.03 | E114: 0.4 | F114: 4.43
A115: Dimanche | B115: 45039 | C115: 19.15 | D115: =Tableau1[[#This Row],[Total €/J]]-Tableau1[[#This Row],[Abonnement €]] -> 3.95 | E115: 0.4 | F115: 4.35
A116: Lundi | B116: 45040 | C116: 13.95 | D116: =Tableau1[[#This Row],[Total €/J]]-Tableau1[[#This Row],[Abonnement €]] -> 2.88 | E116: 0.4 | F116: 3.28
A117: Mardi | B117: 45041 | C117: 18.57 | D117: =Tableau1[[#This Row],[Total €/J]]-Tableau1[[#This Row],[Abonnement €]] -> 3.83 | E117: 0.4 | F117: 4.23
A118: Mercredi | B118: 45042 | C118: 18.49 | D118: =Tableau1[[#This Row],[Total €/J]]-Tableau1[[#This Row],[Abonnement €]] -> 3.82 | E118: 0.4 | F118: 4.22
A119: Jeudi | B119: 45043 | C119: 14.3 | D119: =Tableau1[[#This Row],[Total €/J]]-Tableau1[[#This Row],[Abonnement €]] -> 2.95 | E119: 0.4 | F119: 3.35
A120: Vendredi | B120: 45044 | C120: 16.45 | D120: =Tableau1[[#This Row],[Total €/J]]-Tableau1[[#This Row],[Abonnement €]] -> 3.4 | E120: 0.4 | F120: 3.8
A121: Samedi | B121: 45045 | C121: 17.57 | D121: =Tableau1[[#This Row],[Total €/J]]-Tableau1[[#This Row],[Abonnement €]] -> 3.63 | E121: 0.4 | F121: 4.03
A122: Dimanche | B122: 45046 | C122: 13.06 | D122: =Tableau1[[#This Row],[Total €/J]]-Tableau1[[#This Row],[Abonnement €]] -> 2.7 | E122: 0.4 | F122: 3.1
A123: Lundi | B123: 45047 | C123: 14.38 | D123: =Tableau1[[#This Row],[Total €/J]]-Tableau1[[#This Row],[Abonnement €]] -> 2.96 | E123: 0.4 | F123: 3.36
A124: Mardi | B124: 45048 | C124: 20.79 | D124: =Tableau1[[#This Row],[Total €/J]]-Tableau1[[#This Row],[Abonnement €]] -> 4.28 | E124: 0.4 | F124: 4.68
A125: Mercredi | B125: 45049 | C125: 23.14 | D125: =Tableau1[[#This Row],[Total €/J]]-Tableau1[[#This Row],[Abonnement €]] -> 4.77 | E125: 0.4 | F125: 5.17
... A129: Dimanche | B129: 45053 | C129: 18.26 | D129: =Tableau1[[#This Row],[Total €/J]]-Tableau1[[#This Row],[Abonnement €]] -> 3.76 | E129: 0.4 | F129: 4.16
A130: Lundi | B130: 45054 | C130: 26.31 | D130: =Tableau1[[#This Row],[Total €/J]]-Tableau1[[#This Row],[Abonnement €]] -> 5.42 | E130: 0.4 | F130: 5.82 | G130: 2.17 | H130: Instalaton paneau solaire
A131: Mardi | B131: 45055 | C131: 22.38 | D131: =Tableau1[[#This Row],[Total €/J]]-Tableau1[[#This Row],[Abonnement €]] -> 4.61 | E131: 0.4 | F131: 5.01 | G131: 1.94
A132: Mercredi | B132: 45056 | C132: 18.59 | D132: =Tableau1[[#This Row],[Total €/J]]-Tableau1[[#This Row],[Abonnement €]] -> 3.83 | E132: 0.4 | F132: 4.23 | G132: 4.91
A133: Jeudi | B133: 45057 | C133: 20.82 | D133: =Tableau1[[#This Row],[Total €/J]]-Tableau1[[#This Row],[Abonnement €]] -> 4.29 | E133: 0.4 | F133: 4.69 | G133: 4.07
A134: Vendredi | B134: 45058 | C134: 21.17 | D134: =Tableau1[[#This Row],[Total €/J]]-Tableau1[[#This Row],[Abonnement €]] -> 4.36 | E134: 0.4 | F134: 4.76 | G134: 3.53
A135: Samedi | B135: 45059 | C135: 35.2 | D135: =Tableau1[[#This Row],[Total €/J]]-Tableau1[[#This Row],[Abonnement €]] -> 7.26 | E135: 0.4 | F135: 7.66 | G135: 1.95
A136: Dimanche | B136: 45060 | C136: 19.78 | D136: =Tableau1[[#This Row],[Total €/J]]-Tableau1[[#This Row],[Abonnement €]] -> 3.87 | E136: 0.4 | F136: 4.27 | G136: 5.16 | H136: 9h
A137: Lundi | B137: 45061 | C137: 20.08 | D137: =Tableau1[[#This Row],[Total €/J]]-Tableau1[[#This Row],[Abonnement €]] -> 4.04 | E137: 0.4 | F137: 4.44 | G137: 4.1
A138: Mardi | B138: 45062 | C138: 18.83 | D138: =Tableau1[[#This Row],[Total €/J]]-Tableau1[[#This Row],[Abonnement €]] -> 3.65 | E138: 0.4 | F138: 4.05 | G138: 6.24
A139: Mercredi | B139: 45063 | C139: 22.25 | D139: =Tableau1[[#This Row],[Total €/J]]-Tableau1[[#This Row],[Abonnement €]] -> 4.42 | E139: 0.4 | F139: 4.82 | G139: 5.25
A140: Jeudi | B140: 45064 | C140: 23.66 | D140: =Tableau1[[#This Row],[Total €/J]]-Tableau1[[#This Row],[Abonnement €]] -> 4.79 | E140: 0.4 | F140: 5.19 | G140: 3.62
A141: Vendredi | B141: 45065 | C141: 38.82 | D141: =Tableau1[[#This Row],[Total €/J]]-Tableau1[[#This Row],[Abonnement €]] -> 8.2 | E141: 0.4 | F141: 8.6 | G141: 3.68
A142: Samedi | B142: 45066 | C142: 23.4 | D142: =Tableau1[[#This Row],[Total €/J]]-Tableau1[[#This Row],[Abonnement €]] -> 4.78 | E142: 0.4 | F142: 5.18 | G142: 4.49
A143: Dimanche | B143: 45067 | C143: 24.45 | D143: =Tableau1[[#This Row],[Total €/J]]-Tableau1[[#This Row],[Abonnement €]] -> 5.09 | E143: 0.4 | F143: 5.49 | G143: 1.93
A144: Lundi | B144: 45068 | C144: 20.46 | D144: =Tableau1[[#This Row],[Total €/J]]-Tableau1[[#This Row],[Abonnement €]] -> 4.07 | E144: 0.4 | F144: 4.47 | G144: 4.19
A145: Mardi | B145: 45069 | C145: 16.99 | D145: =Tableau1[[#This Row],[Total €/J]]-Tableau1[[#This Row],[Abonnement €]] -> 3.33 | E145: 0.4 | F145: 3.73 | G145: 4.97
A146: Mercredi | B146: 45070 | C146: 22.04 | D146: =Tableau1[[#This Row],[Total €/J]]-Tableau1[[#This Row],[Abonnement €]] -> 4.46 | E146: 0.4 | F146: 4.86 | G146: 3.43
A147: Jeudi | B147: 45071 | C147: 16.1 | D147: =Tableau1[[#This Row],[Total €/J]]-Tableau1[[#This Row],[Abonnement €]] -> 3.16 | E147: 0.4 | F147: 3.56 | G147: 5.69
A148: Vendredi | B148: 45072 | C148: 13.59 | D148: =Tableau1[[#This Row],[Total €/J]]-Tableau1[[#This Row],[Abonnement €]] -> 2.64 | E148: 0.4 | F148: 3.04 | G148: 6.7
A149: Samedi | B149: 45073 | C149: 16.56 | D149: =Tableau1[[#This Row],[Total €/J]]-Tableau1[[#This Row],[Abonnement €]] -> 3.27 | E149: 0.4 | F149: 3.67 | G149: 6.67
A150: Dimanche | B150: 45074 | C150: 11.39 | D150: =Tableau1[[#This Row],[Total €/J]]-Tableau1[[#This Row],[Abonnement €]] -> 2.08 | E150: 0.4 | F150: 2.48 | G150: 6.38 | H150: 12h
A151: Lundi | B151: 45075 | C151: 21.99 | D151: =Tableau1[[#This Row],[Total €/J]]-Tableau1[[#This Row],[Abonnement €]] -> 4.4 | E151: 0.4 | F151: 4.8 | G151: 5
A152: Mardi | B152: 45076 | C152: 12.64 | D152: =Tableau1[[#This Row],[Total €/J]]-Tableau1[[#This Row],[Abonnement €]] -> 2.38 | E152: 0.4 | F152: 2.78 | G152: 6.53
A153: Mercredi | B153: 45077 | C153: 16.16 | D153: =Tableau1[[#This Row],[Total €/J]]-Tableau1[[#This Row],[Abonnement €]] -> 3.14 | E153: 0.4 | F153: 3.54 | G153: 3.4
A154: Jeudi | B154: 45078 | C154: 15.59 | D154: =Tableau1[[#This Row],[Total €/J]]-Tableau1[[#This Row],[Abonnement €]] -> 3.07 | E154: 0.4 | F154: 3.47 | G154: 5.94
A155: Vendredi | B155: 45079 | C155: 10.24 | D155: =Tableau1[[#This Row],[Total €/J]]-Tableau1[[#This Row],[Abonnement €]] -> 2.1 | E155: 0.4 | F155: 2.5 | G155: 4.5
A156: Samedi | B156: 45080 | C156: 17.67 | D156: =Tableau1[[#This Row],[Total €/J]]-Tableau1[[#This Row],[Abonnement €]] -> 4 | E156: 0.4 | F156: 4.4 | G156: 4.21
A157: Dimanche | B157: 45081 | C157: 8.69 | D157: =Tableau1[[#This Row],[Total €/J]]-Tableau1[[#This Row],[Abonnement €]] -> 1.91 | E157: 0.4 | F157: 2.31 | G157: 5.82
A158: Lundi | B158: 45082 | C158: 7.86 | D158: =Tableau1[[#This Row],[Total €/J]]-Tableau1[[#This Row],[Abonnement €]] -> 1.67 | E158: 0.4 | F158: 2.07 | G158: 6.19
A159: Mardi | B159: 45083 | C159: 7.55 | D159: =Tableau1[[#This Row],[Total €/J]]-Tableau1[[#This Row],[Abonnement €]] -> 1.61 | E159: 0.4 | F159: 2.01 | G159: 5.53
A160: Mercredi | B160: 45084 | C160: 7.19 | D160: =Tableau1[[#This Row],[Total €/J]]-Tableau1[[#This Row],[Abonnement €]] -> 1.47 | E160: 0.4 | F160: 1.87 | G160: 6.5
A161: Jeudi | B161: 45085 | C161: 7.25 | D161: =Tableau1[[#This Row],[Total €/J]]-Tableau1[[#This Row],[Abonnement €]] -> 1.54 | E161: 0.4 | F161: 1.94 | G161: 6.24
A162: Vendredi | B162: 45086 | C162: 11.5 | D162: =Tableau1[[#This Row],[Total €/J]]-Tableau1[[#This Row],[Abonnement €]] -> 2.47 | E162: 0.4 | F162: 2.87 | G162: 2.54
... A169: Vendredi | B169: 45093 | C169: 5.73 | D169: =Tableau1[[#This Row],[Total €/J]]-Tableau1[[#This Row],[Abonnement €]] -> 1.21 | E169: 0.4 | F169: 1.61 | G169: 6.96
A170: Samedi | B170: 45094 | C170: 14.84 | D170: =Tableau1[[#This Row],[Total €/J]]-Tableau1[[#This Row],[Abonnement €]] -> 3.34 | E170: 0.4 | F170: 3.74 | G170: 6.8 | H170: 13h
A171: Dimanche | B171: 45095 | C171: 13.03 | D171: =Tableau1[[#This Row],[Total €/J]]-Tableau1[[#This Row],[Abonnement €]] -> 2.83 | E171: 0.4 | F171: 3.23 | G171: 5.08
A172: Lundi | B172: 45096 | C172: 10.24 | D172: =Tableau1[[#This Row],[Total €/J]]-Tableau1[[#This Row],[Abonnement €]] -> 2.23 | E172: 0.4 | F172: 2.63 | G172: 4.07
A173: Mardi | B173: 45097 | C173: 11.12 | D173: =Tableau1[[#This Row],[Total €/J]]-Tableau1[[#This Row],[Abonnement €]] -> 2.36 | E173: 0.4 | F173: 2.76 | G173: 3.75
A174: Mercredi | B174: 45098 | C174: 11.26 | D174: =Tableau1[[#This Row],[Total €/J]]-Tableau1[[#This Row],[Abonnement €]] -> 2.42 | E174: 0.4 | F174: 2.82 | G174: 4.08
A175: Jeudi | B175: 45099 | C175: 10.67 | D175: =Tableau1[[#This Row],[Total €/J]]-Tableau1[[#This Row],[Abonnement €]] -> 2.32 | E175: 0.4 | F175: 2.72 | G175: 4.38
A176: Vendredi | B176: 45100 | C176: 10.33 | D176: =Tableau1[[#This Row],[Total €/J]]-Tableau1[[#This Row],[Abonnement €]] -> 2.2 | E176: 0.4 | F176: 2.6 | G176: 7.01
A177: Samedi | B177: 45101 | C177: 9.2 | D177: =Tableau1[[#This Row],[Total €/J]]-Tableau1[[#This Row],[Abonnement €]] -> 2.02 | E177: 0.4 | F177: 2.42 | G177: 7.24
A178: Dimanche | B178: 45102 | C178: 8.03 | D178: =Tableau1[[#This Row],[Total €/J]]-Tableau1[[#This Row],[Abonnement €]] -> 1.75 | E178: 0.4 | F178: 2.15 | G178: 7.16
A179: Lundi | B179: 45103 | C179: 9.47 | D179: =Tableau1[[#This Row],[Total €/J]]-Tableau1[[#This Row],[Abonnement €]] -> 2.07 | E179: 0.4 | F179: 2.47 | G179: 5.46
A180: Mardi | B180: 45104 | C180: 6.15 | D180: =Tableau1[[#This Row],[Total €/J]]-Tableau1[[#This Row],[Abonnement €]] -> 1.29 | E180: 0.4 | F180: 1.69 | G180: 6.46
A181: Mercredi | B181: 45105 | C181: 8.39 | D181: =Tableau1[[#This Row],[Total €/J]]-Tableau1[[#This Row],[Abonnement €]] -> 1.79 | E181: 0.4 | F181: 2.19 | G181: 6.35
A182: Jeudi | B182: 45106 | C182: 7.77 | D182: =Tableau1[[#This Row],[Total €/J]]-Tableau1[[#This Row],[Abonnement €]] -> 1.66 | E182: 0.4 | F182: 2.06 | G182: 4.95
... A189: Jeudi | B189: 45113 | C189: 5.48 | D189: =Tableau1[[#This Row],[Total €/J]]-Tableau1[[#This Row],[Abonnement €]] -> 1.18 | E189: 0.4 | F189: 1.58 | G189: 6.62
A190: Vendredi | B190: 45114 | C190: 12.02 | D190: =Tableau1[[#This Row],[Total €/J]]-Tableau1[[#This Row],[Abonnement €]] -> 2.69 | E190: 0.4 | F190: 3.09 | G190: 6.45 | H190: 15h
A191: Samedi | B191: 45115 | C191: 9.43 | D191: =Tableau1[[#This Row],[Total €/J]]-Tableau1[[#This Row],[Abonnement €]] -> 2.05 | E191: 0.4 | F191: 2.45 | G191: 6.56 | H191: 16H
A192: Dimanche | B192: 45116 | C192: 11.59 | D192: =Tableau1[[#This Row],[Total €/J]]-Tableau1[[#This Row],[Abonnement €]] -> 2.45 | E192: 0.4 | F192: 2.85 | G192: 6.77 | H192: 24h
A193: Lundi | B193: 45117 | C193: 15.41 | D193: =Tableau1[[#This Row],[Total €/J]]-Tableau1[[#This Row],[Abonnement €]] -> 2.96 | E193: 0.4 | F193: 3.36 | G193: 6.88
...

Sheet Graf
A1: Année | B1: Janvier | C1: Fevrier | D1: Mars | E1: Avril | F1: Mai | G1: Juin | H1: Juiller | I1: Aout | J1: Septembre | K1: Octobre | L1: Novembre | M1: Decenbre | N1: Année | O1: €/A | P1: KWH/A | Q1: Revente EDF | R1: Coup anuelle | S1: Prix du Kwh Moy | T1: KWH/Moy/M | U1: KWH/Moy/J
A2: 2023 | B2: =Global!C2 -> 541.83 | C2: =Global!C3 -> 447.05 | D2: =Global!C4 -> 417.03 | E2: =Global!C5 -> 406.82 | F2: =Global!C6 -> 637.04 | G2: =Global!C7 -> 302.35 | H2: =Global!C8 -> 353.77 | I2: =Global!C9 -> 387.4 | J2: =Global!C10 -> 338.95 | K2: =Global!C11 -> 314.27 | L2: =Global!C12 -> 366.55 | M2: =Global!C13 -> 443.91 | N2: 2023 | O2: =Global!E15 -> 1183.58 | P2: =Global!C15 -> 4956.97 | Q2: 0 | R2: =O2-Q2 -> 1183.58 | S2: =R2/P2 -> 0.23877086 | T2: =P2/12 -> 413.08083 | U2: =P2/365 -> 13.58074
A3: 2024 | B3: =Global!C18 -> 438.69 | C3: =Global!C19 -> 396.26 | D3: =Global!C20 -> 354.59 | E3: =Global!C21 -> 286.95 | F3: =Global!C22 -> 259.97 | G3: =Global!C23 -> 286.61 | H3: =Global!C24 -> 313.59 | I3: =Global!C25 -> 339.26 | J3: =Global!C26 -> 296.57 | K3: =Global!C27 -> 257.88 | L3: =Global!C28 -> 259.92 | M3: =Global!C29 -> 410.43 | N3: 2024 | O3: =Global!E31 -> 1118.76 | P3: =Global!C31 -> 3900.72 | Q3: 0 | R3: =O3-Q3 -> 1118.76 | S3: =R3/P3 -> 0.28680859 | T3: =P3/12 -> 325.06 | U3: =P3/366 -> 10.657705
A4: 2025 | B4: =Global!C34 -> 404.56 | C4: =Global!C35 -> 269.71 | D4: =Global!C36 -> 249.81 | E4: =Global!C37 -> 154.14 | F4: =Global!C38 -> 155.68 | G4: =Global!C39 -> 167.76 | H4: =Global!C40 -> 131.31 | I4: =Global!C41 -> 246.16 | J4: =Global!C42 -> 151.99 | K4: =Global!C43 -> 205.82 | L4: =Global!C44 -> 322.55 | M4: =Global!C45 -> 360.56 | N4: 2025 | O4: =Global!E47 -> 906.69 | P4: =SUM(B4:M4) -> 2820.05 | Q4: =Kit_Solaire!L12 -> 371.95 | R4: =O4-Q4 -> 534.74 | S4: =R4/P4 -> 0.18962075 | T4: =P4/12 -> 235.00417 | U4: =P4/365 -> 7.7261644
A5: 2026 | B5: =Global!C50 -> 348.45 | C5: =Global!C51 -> 259.3 | D5: =Global!C52 -> 242.69 | E5: =Global!C53 -> 164.38 | F5: =Global!C54 -> 148.12 | G5: =Global!C55 -> 196.12 | H5: =Global!C56 -> 167.51 | I5: =Global!C57 -> 234.42 | J5: =Global!C58 -> 126.71 | N5: 2026 | O5: =Global!E63 -> 639.43 | P5: =Global!C63 -> 1887.7 | Q5: =Kit_Solaire!L13 -> 341.33 | R5: =O5-Q5 -> 298.1 | S5: =Tableau10[[#This Row],[Coup anuelle ]]/Tableau10[[#This Row],[KWH/A]] -> 0.15791704
A6: 2027 | N6: 2027
A7: 2028 | N7: 2028
A8: 2029 | N8: 2029
A9: 2030 | N9: 2030

Sheet EXPORT_SITE
A1: clé | B1: valeur | E1: annee | F1: production_kwh | G1: consommation_kwh | H1: injection_kwh | I1: autoconsommation_kwh | J1: facture_kwh
A2: nom_installation | B2: Maison Albi | E2: 2023 | F2: =Kit_Solaire!E10 -> 904.28 | G2: =Global!C15 -> 4956.97 | H2: =Kit_Solaire!I10 -> 50 | I2: =Tableau11[[#This Row],[production_kwh]]-Tableau11[[#This Row],[injection_kwh]] -> 854.28 | J2: 0
A3: puissance_kwc_Total | B3: =Kit_Solaire!I2 -> 4.11 | E3: 2024 | F3: =Kit_Solaire!E11 -> 1709.17 | G3: =Global!C31 -> 3900.72 | H3: =Kit_Solaire!I11 -> 506 | I3: =Tableau11[[#This Row],[production_kwh]]-Tableau11[[#This Row],[injection_kwh]] -> 1203.17 | J3: 0
A4: nombre_panneaux | B4: 9 | E4: 2025 | F4: =Kit_Solaire!E12 -> 5120.12 | G4: =Global!C47 -> 2820.05 | H4: =Kit_Solaire!I12 -> 2874 | I4: =Tableau11[[#This Row],[production_kwh]]-Tableau11[[#This Row],[injection_kwh]] -> 2246.12 | J4: =Kit_Solaire!O12 -> 2915
A5: Produit_2_date_mise_service | B5: 45582 | E5: 2026 | F5: =Kit_Solaire!E13 -> 4558.98 | G5: =Global!C63 -> 1887.7 | H5: =Kit_Solaire!I13 -> 2608 | I5: =Tableau11[[#This Row],[production_kwh]]-Tableau11[[#This Row],[injection_kwh]] -> 1950.98 | J5: =Kit_Solaire!O13 -> 2675
A6: Produit_1_date_mise_service | B6: 45054 | E6: 2027
A7: cout_installation_Total | B7: =Kit_Solaire!L26 -> 6205.65 | E7: 2028
A8: prix_reference_kwh | B8: =AVERAGE(Kit_Solaire!J10:J17) -> 0.24980167 | E8: 2029
A9: Produit_1_Pan_Sol_PlugAndPlay | B9: =Kit_Solaire!F5 -> 1193.65 | E9: 2030
A10: Produit_2_Pan_Sol_Maison | B10: =Kit_Solaire!G26 -> 5012
A11: Produit_1_puissance_kwc | B11: 1.11
A12: Produit_2_puissance_kwc | B12: 3
A17: indicateur | B17: valeur | E17: Annee | F17: Janvier_kwh | G17: Fevrier_kwh | H17: Mars_kwh | I17: Avril_kwh | J17: Mai_kwh | K17: Juin_kwh | L17: Juiller_kwh | M17: Aout_kwh | N17: Septembre_kwh | O17: Octobre_kwh | P17: Novembre_kwh | Q17: Decenbre_kwh
A18: production_totale | B18: =Global!G15+Global!G31+Global!G47+Global!G63 -> 12292.55 | E18: 2023 | F18: =Graf!B2 -> 541.83 | G18: =Graf!C2 -> 447.05 | H18: =Graf!D2 -> 417.03 | I18: =Graf!E2 -> 406.82 | J18: =Graf!F2 -> 637.04 | K18: =Graf!G2 -> 302.35 | L18: =Graf!H2 -> 353.77 | M18: =Graf!I2 -> 387.4 | ... Q18: =Graf!M2 -> 443.91
A19: consommation_totale | B19: =Graf!P2+Graf!P3+Graf!P4+Graf!P5+Graf!P6+Graf!P7+Graf!P8 -> 13565.44 | E19: 2024 | F19: =Graf!B3 -> 438.69 | G19: =Graf!C3 -> 396.26 | H19: =Graf!D3 -> 354.59 | I19: =Graf!E3 -> 286.95 | J19: =Graf!F3 -> 259.97 | K19: =Graf!G3 -> 286.61 | L19: =Graf!H3 -> 313.59 | M19: =Graf!I3 -> 339.26 | ... Q19: =Graf!M3 -> 410.43
A20: injection_totale | B20: =Kit_Solaire!I18 -> 6038 | E20: 2025 | F20: =Graf!B4 -> 404.56 | G20: =Graf!C4 -> 269.71 | H20: =Graf!D4 -> 249.81 | I20: =Graf!E4 -> 154.14 | J20: =Graf!F4 -> 155.68 | K20: =Graf!G4 -> 167.76 | L20: =Graf!H4 -> 131.31 | M20: =Graf!I4 -> 246.16 | ... Q20: =Graf!M4 -> 360.56
A21: economie_totale | B21: =Kit_Solaire!L2 -> 2316.3827 | E21: 2026 | F21: =Graf!B5 -> 348.45 | G21: =Graf!C5 -> 259.3 | H21: =Graf!D5 -> 242.69 | I21: =Graf!E5 -> 164.38 | J21: =Graf!F5 -> 148.12 | K21: =Graf!G5 -> 196.12 | L21: =Graf!H5 -> 167.51 | M21: =Graf!I5 -> 234.42 | ... Q21: =Graf!M5 -> 0
A22: amortissement_euro | B22: =Kit_Solaire!N2 -> -3889.2673 | E22: 2027
A23: amortissement_pourcent | B23: =B21/B7 -> 0.37326996 | E23: 2028
E24: 2029
E25: 2030

Sheet PARAMETRES_COCKPIT
A1: Cockpit solaire — paramètres & contexte
A2: Clé | B2: Valeur | C2: Unité / format | D2: Source / note
A3: first_full_solar_year | B3: 2025 | C3: année | D3: Première année complète avec les deux installations
A4: plug_power_kwc | B4: 1.11 | C4: kWc | D4: Kit plug-and-play
A5: plug_orientation | B5: Ouest | C5: texte | D5: Contexte utilisateur
A6: plug_service_date | B6: 45054 | C6: date | D6: Classeur / mise en service
A7: plug_role | B7: Compensation initiale de la consommation de la piscine, puis complément de production en fin de journée | C7: texte | D7: Contexte utilisateur
A8: main_power_kwc | B8: 3 | C8: kWc | D8: Installation toiture Kbane / DualSun
A9: main_orientation | B9: Plein sud, légère composante ouest | C9: texte | D9: Contexte utilisateur
A10: main_service_date | B10: 45582 | C10: date | D10: Classeur / mise en service
A11: main_shading_note | B11: Ombre ponctuelle d'un arbre voisin surtout en hiver, environ 10 h à 11 h | C11: texte | D11: Contexte utilisateur
A12: pool_surface_m2_est | B12: 9.89 | C12: m² | D12: Dimensions approximatives 2,30 × 4,30 m
A13: pool_water_depth_m | B13: 1.3 | C13: m | D13: Niveau d'eau utile approximatif
A14: pool_volume_m3_est | B14: 12.857 | C14: m³ | D14: Estimation géométrique, hors formes/parois
A15: pool_pump_power_w | B15: 750 | C15: W | D15: Puissance pompe communiquée
A16: pool_summer_runtime_low_h | B16: 8 | C16: h/j | D16: Filtration typique été : environ 9/10 h → 18 h
A17: pool_summer_runtime_high_h | B17: 9 | C17: h/j | D17: Filtration typique été : environ 9/10 h → 18 h
A18: pool_summer_daily_kwh_low | B18: 6 | C18: kWh/j | D18: Calcul 0,75 kW × 8 h
A19: pool_summer_daily_kwh_high | B19: 6.75 | C19: kWh/j | D19: Calcul 0,75 kW × 9 h
A20: edf_oa_tariff_eur_kwh | B20: 0.1276 | C20: €/kWh | D20: Contrat EDF OA
A21: edf_oa_2025_invoice_start | B21: 45614 | C21: date | D21: Facture EDF OA 2025
A22: edf_oa_2025_invoice_end | B22: 45978 | C22: date | D22: Facture EDF OA 2025
A23: edf_oa_2025_invoice_kwh | B23: 2915 | C23: kWh | D23: Facture EDF OA 2025
A24: edf_oa_2025_invoice_eur | B24: 371.95 | C24: € | D24: Facture EDF OA 2025
A25: note_oa_calendar | B25: La revente facturée suit une période de facturation EDF OA et non strictement l'année civile. | C25: texte | D25: Règle de lecture
A26: note_weather | B26: Température/pluie contextualisent la production mais ne remplacent pas une mesure d'irradiation solaire. | C26: texte | D26: Règle de lecture
A27: note_injection_monthly | B27: Sans injection mensuelle réelle, toute ventilation mensuelle de l'injection est une estimation. | C27: texte | D27: Règle de lecture
